{
  "2026-06-09": {
    "keyword_tags": [
      "男生穿搭",
      "美式復古",
      "阿美咔嘰"
    ],
    "ai_summary": {
      "title": "今日 Threads 穿搭熱門趨勢追蹤",
      "intro": "今日 Threads 穿搭社群呈現出實用導向與風格探討並進的趨勢。用戶高度關注「比例修正」與「身形條件」對風格呈現的影響，特別是針對男性的五五身改造建議引起廣泛討論。此外，對於韓、日、美、法式風格的精髓總結，以及結合 AI 創作的美式街頭塗鴉復古風，顯示出社群對多元視覺與傳統剪裁規則的重新審視。",
      "highlights": [
        {
          "title": "男生五五身比例改造求助",
          "description": "網友提出關於男性五五身比例的穿搭困擾，討論如何擺脫傳統紮衣服的刻板穿法，尋求更適合「比例不佳」身材的改造方案，反映出男性穿搭市場對進階層次感的渴望。",
          "url": "https://www.threads.com/@bat.4602100/post/DXUZr3DkW01"
        },
        {
          "title": "萬能風格的共通點：薄片人身形",
          "description": "一則關於韓、日、美、法式穿搭精髓的分析獲得極高共鳴，指出無論何種風格，薄瘦的身形往往是呈現美感的基礎，引發社群對「衣架子」與穿搭技術之間關係的省思。",
          "url": "https://www.threads.com/@xwwxz_1221/post/DWLmiYzFYj4"
        },
        {
          "title": "AI 演繹的美式街頭塗鴉復古風",
          "description": "融合了美式街頭感與動漫元素的視覺分享，展示了 2026 年預測性的時尚視角，強調將強烈色彩與塗鴉文化融入日常穿搭的復古美學。",
          "url": "https://www.threads.com/@nini890712/post/DY88J_KCdL_"
        }
      ]
    },
    "posts": [
      {
        "permalink": "https://www.threads.com/@bat.4602100/post/DXUZr3DkW01",
        "username": "bat.4602100",
        "post_date": "2026-4-19",
        "content": "大家好\n想請問一下各位懂穿搭的男生帥哥們🤣\n最近想幫老公改造一下穿衣風格\n才發現他身材比例很不好哈哈\n大概是五五身\n這樣的身材比例要怎麼穿才不會顯得很矮\n我上網查到是說把上衣紮進去褲子裡\n但他也似乎不適合🤣穿起來很好笑\n還有別的方法嗎？\n不然看他永遠只會穿合身牛仔褲上面加一件素t\n先謝謝各位的回覆了🥹",
        "likes": 33,
        "comments": 46,
        "reposts": 3,
        "shares": 0,
        "keyword": "男生穿搭"
      },
      {
        "permalink": "https://www.threads.com/@deepbreath.9/post/DXvtH6CEdtT",
        "username": "deepbreath.9",
        "post_date": "2026-4-30",
        "content": "筆記一下\n北美館超現實主義展的各種符號",
        "likes": 420,
        "comments": 26,
        "reposts": 33,
        "shares": 48,
        "keyword": "美式復古"
      },
      {
        "permalink": "https://www.threads.com/@xwwxz_1221/post/DWLmiYzFYj4",
        "username": "xwwxz_1221",
        "post_date": "2026-3-22",
        "content": "其实韩式日式美式法式穿搭精髓都是薄薄一片人😭😭😭😭",
        "likes": 7450,
        "comments": 43,
        "reposts": 389,
        "shares": 147,
        "keyword": "美式復古"
      },
      {
        "permalink": "https://www.threads.com/@lp99_520_521/post/DYMqyKslHPT",
        "username": "lp99_520_521",
        "post_date": "2026-5-11",
        "content": "看來現在很流行這種裝潢風格喔\n￼我要不要也來弄一個?🤭",
        "likes": 518,
        "comments": 14,
        "reposts": 16,
        "shares": 17,
        "keyword": "美式復古"
      },
      {
        "permalink": "https://www.threads.com/@nini890712/post/DY88J_KCdL_",
        "username": "nini890712",
        "post_date": "2026-5-30",
        "content": "哇！喜歡這種風格……🥰\n美式街頭塗鴉風還+上我的庫洛米\nlina_aling84\nAI Threads\n2026-5-29\nFashion Queen ✨ Walking through the city like it's my personal runway. 💜🖤\nImage : GPT\nPrompt⤵️",
        "likes": 38,
        "comments": 22,
        "reposts": 6,
        "shares": 4,
        "keyword": "美式復古"
      },
      {
        "permalink": "https://www.threads.com/@lina_aling84/post/DY6fVh4CaDe",
        "username": "lina_aling84",
        "post_date": "2026-5-29",
        "content": "Fashion Queen ✨ Walking through the city like it's my personal runway. 💜🖤\nImage : GPT\nPrompt⤵️",
        "likes": 38,
        "comments": 22,
        "reposts": 6,
        "shares": 4,
        "keyword": "美式復古"
      },
      {
        "permalink": "https://www.threads.com/@armymimimi7/post/DZD6hOaAeCC",
        "username": "armymimimi7",
        "post_date": "2026-6-1",
        "content": "好想和阿米互关。",
        "likes": 8,
        "comments": 13,
        "reposts": 0,
        "shares": 0,
        "keyword": "阿美咔嘰"
      },
      {
        "permalink": "https://www.threads.com/@charlotte_ellie_yen/post/DYPRIO3lAfM",
        "username": "charlotte_ellie_yen",
        "post_date": "2026-5-12",
        "content": "阿美最後一場IMAX🥹",
        "likes": 61,
        "comments": 6,
        "reposts": 7,
        "shares": 0,
        "keyword": "阿美咔嘰"
      },
      {
        "permalink": "https://www.threads.com/@wxplbxsk/post/DYWjkkHiYKh",
        "username": "wxplbxsk",
        "post_date": "2026-5-15",
        "content": "？安美塞了一大疊特典給我 這對嗎",
        "likes": 237,
        "comments": 162,
        "reposts": 1,
        "shares": 47,
        "keyword": "阿美咔嘰"
      },
      {
        "permalink": "https://www.threads.com/@guiishun/post/DZEzxQYkjQU",
        "username": "guiishun",
        "post_date": "6天",
        "content": "阿米棒阿米棒阿米棒4",
        "likes": 8,
        "comments": 0,
        "reposts": 0,
        "shares": 0,
        "keyword": "阿美咔嘰"
      },
      {
        "permalink": "https://www.threads.com/@shan_btsforever/post/DYZn9IPEXSm",
        "username": "shan_btsforever",
        "post_date": "2026-5-16",
        "content": "把阿米放在手上和心裡的柾國💜\n(以下雷國旻勿開）\n是說下次補色的時候不要只補JM，\n請同步補一下R謝謝\n不然我們即將成為AMY😌",
        "likes": 474,
        "comments": 13,
        "reposts": 10,
        "shares": 18,
        "keyword": "阿美咔嘰"
      }
    ]
  },
  "2026-06-08": {
    "keyword_tags": [
      "男生穿搭",
      "美式復古",
      "阿美咔嘰"
    ],
    "ai_summary": {
      "title": "今日 Threads 穿搭熱門趨勢追蹤：跨性別優雅與復古混搭潮流",
      "intro": "今日社群觀察顯示，男性穿搭正朝向更為「優雅」與「無性別界線」的方向發展，強調體態管理與自信展現。此外，二手與古著（Vintage）文化依然強勁，特別是結合日韓系與美式風格的選物熱潮。社群對於『復古』的追求也延伸至空間美學，反映出對老派工藝與年代感的集體共鳴。",
      "highlights": [
        {
          "title": "男性穿搭的新優雅定義",
          "description": "網友分享男生穿著女裝展現美感的穿搭實驗，強調「優雅」不應受性別限制，雖然維持體態與儀態相對辛苦，但精緻的視覺效果已成為男性時尚的新嘗試方向。",
          "url": "https://www.threads.com/@duke851120/post/DX19Xxpk8yr"
        },
        {
          "title": "多元復古風格的二手選物熱潮",
          "description": "涵蓋日韓系與美式風格的全新及二手衣物交易資訊，反映出 Threads 使用者對於高 CP 值與獨特性復古單品的強烈需求與高度關注。",
          "url": "https://www.threads.com/@xoxo____3miii/post/DWlR2o9FOYC"
        },
        {
          "title": "尋找日常中的復古老派靈感",
          "description": "透過觀察老字號百貨公司的復古雕花與大理石設計，探討在極簡風盛行的現代，經典工藝如何轉化為生活與穿搭的優雅靈感來源。",
          "url": "https://www.threads.com/@hung_shiun/post/DZShPBamB06"
        }
      ]
    },
    "posts": [
      {
        "permalink": "https://www.threads.com/@duke851120/post/DX19Xxpk8yr",
        "username": "duke851120",
        "post_date": "2026-5-2",
        "content": "男的\n最近喜歡上這類的穿搭，走路都要很優雅不能駝背\n超累的衣服，但是我很喜歡，男生穿女裝也可以很美🥰",
        "likes": 178,
        "comments": 17,
        "reposts": 3,
        "shares": 7,
        "keyword": "男生穿搭"
      },
      {
        "permalink": "https://www.threads.com/@xoxo____3miii/post/DWlR2o9FOYC",
        "username": "xoxo____3miii",
        "post_date": "2026-4-1",
        "content": "➗日韓系/美式全新/二手衣 🌲🪽🌀☆ ໒꒱ ‧₊\n⋆˚✿˖⋆˚✿˖ ⋆˚✿˖⋆˚✿˖ ⋆˚✿˖⋆˚✿˖ ⋆˚✿˖⋆˚✿˖",
        "likes": 611,
        "comments": 56,
        "reposts": 16,
        "shares": 62,
        "keyword": "美式復古"
      },
      {
        "permalink": "https://www.threads.com/@hung_shiun/post/DZShPBamB06",
        "username": "hung_shiun",
        "post_date": "14小時",
        "content": "現在的百貨公司，竟然還看得到這種老派的復古雕花欄杆？\n​週末逛街逛到一半，走到樓梯間，還以為自己不小心穿越了時空！\n​在這個到處都是極簡風與透明玻璃的時代，竟然還有這種充滿年代感、工藝極度繁複的金屬雕花欄杆\n​大理石牆面配上金色的藤蔓圖騰，有一種專屬於老字號百貨的優雅跟氣派\n​它不是現在那種刻意做舊的網美裝潢！​而是真的靜靜待在那裡，承載了「這個地區」幾十年的繁華歲月\n​\n大家能猜的出來是哪一間百貨公司嗎？",
        "likes": 8,
        "comments": 3,
        "reposts": 0,
        "shares": 0,
        "keyword": "美式復古"
      },
      {
        "permalink": "https://www.threads.com/@choudi9126_/post/DY3tN2MEW3u",
        "username": "choudi9126_",
        "post_date": "2026-5-28",
        "content": "他們會幫米圈創造屬於阿米的梗圖系列",
        "likes": 524,
        "comments": 1,
        "reposts": 32,
        "shares": 17,
        "keyword": "阿美咔嘰"
      },
      {
        "permalink": "https://www.threads.com/@con_stance105/post/DX4LpFOj0Xl",
        "username": "con_stance105",
        "post_date": "2026-5-3",
        "content": "希望你知道，阿Mike 的好",
        "likes": 660,
        "comments": 28,
        "reposts": 10,
        "shares": 1176,
        "keyword": "阿美咔嘰"
      }
    ]
  },
  "2026-06-07": {
    "keyword_tags": [
      "男生穿搭",
      "美式復古",
      "阿美咔嘰"
    ],
    "ai_summary": {
      "title": "今日 Threads 穿搭熱門趨勢：健體風男裝與古典復刻美學",
      "intro": "今日 Threads 穿搭社群展現出兩極化的趨勢。在男裝領域，「Muscle Fit」與強調身形線條的簡約搭配成為熱門焦點，男性使用者對於高效單品與店鋪推薦的互動極高。在風格美學上，討論從主流復古延伸至 19 世紀西洋古典服飾及具個性化的婚紗穿搭，顯示使用者正從大眾流行轉向追求高辨識度的「風格復刻」。",
      "highlights": [
        {
          "title": "男性穿搭的「懶人鎖定」效應",
          "description": "獲得超過三千個讚的貼文指出，能讓男生「直接鎖在身上」的高質感關鍵單品極具吸引力，顯示男性社群在尋找具備高度實穿性且不需複雜思考的穿搭方案。",
          "url": "https://www.threads.com/@omgomg_8887/post/DTFxW7zE7ZR"
        },
        {
          "title": "19 世紀西洋古典風格的復刻討論",
          "description": "使用者分享對 19 世紀帝政裙與高腰剪裁的迷戀，引起近六千次讚數，顯示極小眾的古典復刻美學在社群中正透過「堅持喜好」的共鳴感逐漸擴大影響力。",
          "url": "https://www.threads.com/@ladyl.2015/post/DXuOlYvE4IG"
        },
        {
          "title": "夏日男裝：Muscle Fit 與身材建模",
          "description": "今年夏天社群推崇以健身為基礎的「身材建模」穿搭，建議合身上衣搭配直筒褲，將穿搭重點從衣服轉向對身形線條的強化。",
          "url": "https://www.threads.com/@erichang.style/post/DXRM0wLgOp_"
        },
        {
          "title": "風格婚紗：打破傳統的視覺美學",
          "description": "一篇關於「最特別婚紗照」的貼文獲得 2.9 萬高額互動，顯示出當穿搭美學應用於婚紗等特定場景時，跳脫傳統限制的獨特風格最能引發社群熱議。",
          "url": "https://www.threads.com/@ping.__14/post/DV0RJtbk9Bs"
        }
      ]
    },
    "posts": [
      {
        "permalink": "https://www.threads.com/@erichang.style/post/DXRM0wLgOp_",
        "username": "erichang.style",
        "post_date": "2026-4-18",
        "content": "今年夏天男生穿搭一律建議：加強身材建模，然後muscle fit 上衣+直筒褲✌️",
        "likes": 58,
        "comments": 10,
        "reposts": 2,
        "shares": 8,
        "keyword": "男生穿搭"
      },
      {
        "permalink": "https://www.threads.com/@omgomg_8887/post/DTFxW7zE7ZR",
        "username": "omgomg_8887",
        "post_date": "2026-1-4",
        "content": "男生不懂穿搭的 直接把這件鎖在身上🫡",
        "likes": 3445,
        "comments": 116,
        "reposts": 94,
        "shares": 2653,
        "keyword": "男生穿搭"
      },
      {
        "permalink": "https://www.threads.com/@kai__7__7/post/DXssd15k9ce",
        "username": "kai__7__7",
        "post_date": "2026-4-29",
        "content": "請推薦我\n男生 素色 挺挺 好看的 短袖套裝🫡",
        "likes": 11,
        "comments": 11,
        "reposts": 5,
        "shares": 0,
        "keyword": "男生穿搭"
      },
      {
        "permalink": "https://www.threads.com/@vonjcas/post/DNmi8UAylCa",
        "username": "vonjcas",
        "post_date": "2025-8-21",
        "content": "男生想買衣服的可以來這間看看👀",
        "likes": 1615,
        "comments": 3,
        "reposts": 120,
        "shares": 965,
        "keyword": "男生穿搭"
      },
      {
        "permalink": "https://www.threads.com/@ladyl.2015/post/DXuOlYvE4IG",
        "username": "ladyl.2015",
        "post_date": "2026-4-29",
        "content": "最近看到有人在復刻清朝服飾走在路上\n蠻羨慕也佩服他對於喜好的堅持\n想問脆上有人也喜歡\n19世紀初西洋女性服飾 / 帝政裙 嗎？\n那種復古的高腰剪裁跟古典美真的好迷人，\n好想知道台灣有沒有人在玩這時期的復刻或穿搭？",
        "likes": 5869,
        "comments": 235,
        "reposts": 215,
        "shares": 219,
        "keyword": "美式復古"
      },
      {
        "permalink": "https://www.threads.com/@__cc.w__/post/DW1CaVokXj9",
        "username": "__cc.w__",
        "post_date": "2026-4-7",
        "content": "想請問有人的家裡是以台式風格裝潢的嗎？\n看了一些雜誌 都是日式、北歐風居多\n台式風格的話我能夠想到一些元素 例如 竹、籐、花磚、磨石子\n但不知道是不是只能朝復古懷舊風去裝潢？或者可以讓它更具現代感？",
        "likes": 7,
        "comments": 7,
        "reposts": 0,
        "shares": 0,
        "keyword": "美式復古"
      },
      {
        "permalink": "https://www.threads.com/@sandy331313/post/DY2JrY_mqqV",
        "username": "sandy331313",
        "post_date": "2026-5-27",
        "content": "想問有類似這種風格的服飾網拍嗎🙏簡約又韓系風格的，希望能平價一點",
        "likes": 3,
        "comments": 7,
        "reposts": 0,
        "shares": 0,
        "keyword": "美式復古"
      },
      {
        "permalink": "https://www.threads.com/@_e.1_a/post/DU5paJOCUQ7",
        "username": "_e.1_a",
        "post_date": "2026-2-18",
        "content": "好想知道這種風格叫什麼..\n找不到人訂製💔💔",
        "likes": 2753,
        "comments": 20,
        "reposts": 25,
        "shares": 39,
        "keyword": "美式復古"
      },
      {
        "permalink": "https://www.threads.com/@ping.__14/post/DV0RJtbk9Bs",
        "username": "ping.__14",
        "post_date": "2026-3-13",
        "content": "想蓋個樓\n《最特別的婚紗照》\n我先來 我姐的😻",
        "likes": 29000,
        "comments": 1476,
        "reposts": 280,
        "shares": 3110,
        "keyword": "阿美咔嘰"
      },
      {
        "permalink": "https://www.threads.com/@able_0416/post/DV03FJBgQjM",
        "username": "able_0416",
        "post_date": "2026-3-13",
        "content": "阿美族🌾",
        "likes": 15000,
        "comments": 158,
        "reposts": 45,
        "shares": 121,
        "keyword": "阿美咔嘰"
      },
      {
        "permalink": "https://www.threads.com/@a_168_88/post/DXWZxn6mdVQ",
        "username": "a_168_88",
        "post_date": "2026-4-20",
        "content": "高火安美進新娃了\nSumimi初華Get!\n我看裡面還有阿拉蕾\n甜甜圈女士也有🍩",
        "likes": 378,
        "comments": 29,
        "reposts": 8,
        "shares": 168,
        "keyword": "阿美咔嘰"
      },
      {
        "permalink": "https://www.threads.com/@ren16nie/post/DY3amjsgUbW",
        "username": "ren16nie",
        "post_date": "2026-5-28",
        "content": "想蓋個原住民顏值樓\n男女都可以 不知道蓋不蓋得起來",
        "likes": 6065,
        "comments": 1049,
        "reposts": 78,
        "shares": 489,
        "keyword": "阿美咔嘰"
      },
      {
        "permalink": "https://www.threads.com/@sum_mer0724/post/DY9FGe2EeFt",
        "username": "sum_mer0724",
        "post_date": "2026-5-30",
        "content": "阿美一半",
        "likes": 82,
        "comments": 3,
        "reposts": 0,
        "shares": 0,
        "keyword": "阿美咔嘰"
      }
    ]
  },
  "2026-06-06": {
    "keyword_tags": [
      "男生穿搭",
      "美式復古",
      "阿美咔嘰"
    ],
    "ai_summary": {
      "title": "今日 Threads 穿搭趨勢報告：中性化美學與實用主義的崛起",
      "intro": "今日 Threads 穿搭討論集中於男裝風格的演變，核心趨勢圍繞「模糊性別框架」以及「穿搭細節管理」。數據顯示，男性嘗試女裝的討論度極高，反映出 Genderless 風格正滲透進入日常社群；同時，實用主義穿搭（如口袋管理、俐落廓形）依然是男裝社群中的教條。值得注意的是，部分復古標籤（如阿美咔嘰）在社群中存在關鍵字混淆現象，但穿搭核心內容仍保持高度互動。",
      "highlights": [
        {
          "title": "無性別美學：男裝女穿的風格探索",
          "description": "針對男生購買女裝進行穿搭的現象引發熱議，反映出 Threads 用戶對打破傳統服飾性別界線的包容度與嘗試意願，獲得極高互動量。",
          "url": "https://www.threads.com/@secallenyang/post/DN2TPz23l2W"
        },
        {
          "title": "實用主義美學：俐落廓形的口袋管理",
          "description": "穿搭博主提出「口袋不放東西」的實用建議，強調男裝造型中對服裝輪廓的維護，此類具備實操性的微細節教學深受用戶喜愛。",
          "url": "https://www.threads.com/@xiangrenyu/post/DIvm0UCTzhp"
        },
        {
          "title": "清新少年感：大男孩風格的穿搭示範",
          "description": "以清新、低負擔的風格定位「小男生穿搭」，展現了休閒與生活感並重的審美趨勢，吸引大量對日常穿搭有需求的用戶關注。",
          "url": "https://www.threads.com/@c.iceyyy/post/DBOk8DcyXrq"
        },
        {
          "title": "服飾與氣韻：同一單品的多元詮釋",
          "description": "探討服飾美學與個人特質的結合，強調服裝不只是覆蓋物，而是個人品味與生活方式的延伸，獲得極高的社群點讚數。",
          "url": "https://www.threads.com/@bjianyu2026/post/DW0jVeODEID"
        }
      ]
    },
    "posts": [
      {
        "permalink": "https://www.threads.com/@secallenyang/post/DN2TPz23l2W",
        "username": "secallenyang",
        "post_date": "2025-8-27",
        "content": "全部買女裝，這樣算有異裝癖嗎？",
        "likes": 2323,
        "comments": 67,
        "reposts": 54,
        "shares": 588,
        "keyword": "男生穿搭"
      },
      {
        "permalink": "https://www.threads.com/@xiangrenyu/post/DIvm0UCTzhp",
        "username": "xiangrenyu",
        "post_date": "2025-4-22",
        "content": "男生穿搭術，第一招：\n褲子口袋 別放東西...\n拜託 😂",
        "likes": 2481,
        "comments": 326,
        "reposts": 4,
        "shares": 81,
        "keyword": "男生穿搭"
      },
      {
        "permalink": "https://www.threads.com/@c.iceyyy/post/DBOk8DcyXrq",
        "username": "c.iceyyy",
        "post_date": "2024-10-17",
        "content": "小男生穿搭☕️🙂‍↔️",
        "likes": 3517,
        "comments": 130,
        "reposts": 3,
        "shares": 98,
        "keyword": "男生穿搭"
      },
      {
        "permalink": "https://www.threads.com/@bjianyu2026/post/DW0jVeODEID",
        "username": "bjianyu2026",
        "post_date": "2026-4-7",
        "content": "同款衣衫\n有人穿成诗\n有人穿成生活。\n#时尚 #美学",
        "likes": 8980,
        "comments": 57,
        "reposts": 227,
        "shares": 3821,
        "keyword": "男生穿搭"
      },
      {
        "permalink": "https://www.threads.com/@cry.laugh/post/DWJQ2ksAWH0",
        "username": "cry.laugh",
        "post_date": "2026-3-21",
        "content": "麻煩脆上大神給點建議\n我想軟裝改成北歐現代的感覺 🥹",
        "likes": 137,
        "comments": 74,
        "reposts": 1,
        "shares": 44,
        "keyword": "美式復古"
      },
      {
        "permalink": "https://www.threads.com/@jin_xi94/post/DYoJfMRElrm",
        "username": "jin_xi94",
        "post_date": "2026-5-22",
        "content": "好奇大家的風格會是什麼樣子",
        "likes": 97,
        "comments": 43,
        "reposts": 6,
        "shares": 63,
        "keyword": "美式復古"
      },
      {
        "permalink": "https://www.threads.com/@loo._.117/post/DYJc8nLk97N",
        "username": "loo._.117",
        "post_date": "2026-5-10",
        "content": "哇哇哇又可以看到跟別人cha 這個女生是誰阿 好漂亮！\nbabymonster_ygofficial",
        "likes": 697,
        "comments": 20,
        "reposts": 4,
        "shares": 2,
        "keyword": "阿美咔嘰"
      },
      {
        "permalink": "https://www.threads.com/@christyy_.y/post/DTPAt0ckXWG",
        "username": "christyy_.y",
        "post_date": "2026-1-8",
        "content": "我是阿美族了！！！",
        "likes": 348,
        "comments": 21,
        "reposts": 3,
        "shares": 10,
        "keyword": "阿美咔嘰"
      },
      {
        "permalink": "https://www.threads.com/@jia.0531_/post/DYcTjC7k8l6",
        "username": "jia.0531_",
        "post_date": "2026-5-17",
        "content": "就是 那個 脆好像很萬能\n想問有沒有在「台中」的「原住民」可以認識🫠\n每次想要出去喝酒或吃飯完完全全找不到人🤯\n白浪完全get不到我的點😭而且也真的很難聊起來\n不管男生女生 只要是原住民可不可以在下面留言互相認識然後我創個群🫶🏻🥹\n（棒球大大大大大加分）",
        "likes": 404,
        "comments": 153,
        "reposts": 1,
        "shares": 75,
        "keyword": "阿美咔嘰"
      },
      {
        "permalink": "https://www.threads.com/@mikolove0415/post/DYeg2fnkxy6",
        "username": "mikolove0415",
        "post_date": "2026-5-18",
        "content": "台東阿美",
        "likes": 9,
        "comments": 1,
        "reposts": 0,
        "shares": 0,
        "keyword": "阿美咔嘰"
      },
      {
        "permalink": "https://www.threads.com/@linp05460/post/DXbk7t7ky0v",
        "username": "linp05460",
        "post_date": "2026-4-22",
        "content": "到底哪個天才阿米做出來的！\njungkook_army.04",
        "likes": 4187,
        "comments": 68,
        "reposts": 239,
        "shares": 940,
        "keyword": "阿美咔嘰"
      }
    ]
  },
  "2026-06-05": {
    "keyword_tags": [
      "男生穿搭",
      "美式復古",
      "阿美咔嘰"
    ],
    "ai_summary": {
      "title": "今日 Threads 穿搭趨勢報告：韓系審美主導與在地復古風格探索",
      "intro": "今日 Threads 上的男裝穿搭討論極其熱絡，主要呈現兩大核心方向：第一是「韓系精緻化」，從配色原則到選品店推薦，韓系簡約感已成為台港男士提升穿搭的首選參考；第二是「在地風格的尋根」，社群開始熱烈討論何謂真正的港式風格，並試圖將其與復古元素重新連結。整體數據顯示，實用性的配色教學與具有自我主張的穿搭態度最能引起共鳴。",
      "highlights": [
        {
          "title": "韓系配色原則成為萬人關注焦點",
          "description": "貼文強調男生穿搭只要掌握韓系配色邏輯即可大幅提升質感，獲得超過萬次點讚，顯示社群對「系統化穿搭公式」的極高渴求。",
          "url": "https://www.threads.com/@henryhohoha/post/DSmjafgAbrG"
        },
        {
          "title": "「男友改造計畫」：從運動男孩轉型韓系風格",
          "description": "透過女性視角分享另一半穿搭風格的轉變，顯示韓系風格在異性審美中亦佔據高位，進一步推動了韓風男裝的流行度。",
          "url": "https://www.threads.com/@pudding910410/post/DUuYzKiE0Iv"
        },
        {
          "title": "探索本土港式風格與復古的關聯",
          "description": "網友發起關於「香港原創風格」的討論，探究港式穿搭是否等同於復古風，引發對日韓流行文化之外的在地審美思考。",
          "url": "https://www.threads.com/@spilltheteaandmeal/post/DYmV7D-AIRA"
        },
        {
          "title": "台灣男生必逛的五間質感選品店推薦",
          "description": "針對想提升穿搭質感的台灣男生提供具體的通路建議，這類懶人包式的選品導引在 Threads 上具有極高的導購與收藏價值。",
          "url": "https://www.threads.com/@mira_select_/post/DPeLoQeiUqV"
        }
      ]
    },
    "posts": [
      {
        "permalink": "https://www.threads.com/@henryhohoha/post/DSmjafgAbrG",
        "username": "henryhohoha",
        "post_date": "2025-12-23",
        "content": "男生學穿搭 像韓國男生這樣把握配色原則\n真的起碼80分以上🙂‍↕️",
        "likes": 11000,
        "comments": 169,
        "reposts": 694,
        "shares": 5009,
        "keyword": "男生穿搭"
      },
      {
        "permalink": "https://www.threads.com/@roger_iamreallyfuck/post/DSo3k7zkrDT",
        "username": "roger_iamreallyfuck",
        "post_date": "2025-12-24",
        "content": "我這套直接屌贏你那些2486穿搭",
        "likes": 11000,
        "comments": 35,
        "reposts": 130,
        "shares": 1356,
        "keyword": "男生穿搭"
      },
      {
        "permalink": "https://www.threads.com/@pudding910410/post/DUuYzKiE0Iv",
        "username": "pudding910410",
        "post_date": "2026-2-14",
        "content": "當你有個賣衣服的女友\n另一半的穿搭風格會從運動男孩變韓系男孩",
        "likes": 9309,
        "comments": 1126,
        "reposts": 36,
        "shares": 1518,
        "keyword": "男生穿搭"
      },
      {
        "permalink": "https://www.threads.com/@___h.e.r.a/post/DVYW2fCD-Cn",
        "username": "___h.e.r.a",
        "post_date": "2026-3-2",
        "content": "心動小鎮的男生\n好看穿搭是不是很少？\n女裝好像比較多\n想看穿搭圖 男生女生都行",
        "likes": 715,
        "comments": 108,
        "reposts": 16,
        "shares": 141,
        "keyword": "男生穿搭"
      },
      {
        "permalink": "https://www.threads.com/@mira_select_/post/DPeLoQeiUqV",
        "username": "mira_select_",
        "post_date": "2025-10-6",
        "content": "台灣男生想提升穿搭絕對要逛這5間店🤩",
        "likes": 1315,
        "comments": 6,
        "reposts": 109,
        "shares": 1244,
        "keyword": "男生穿搭"
      },
      {
        "permalink": "https://www.threads.com/@mkt_iloveart/post/DYePnO1D4Ng",
        "username": "mkt_iloveart",
        "post_date": "2026-5-18",
        "content": "其實「日系小清新」呢種攝影風格已經過氣\n唔好話日韓 連大陸同台灣都無乜人玩\n唔明點解香港啲攝影班仲係教緊呢種style\n小清新由流行到依家都起碼過咗6-7年啦\n審美trend都已經換咗幾輪\n學下新嘢吧",
        "likes": 63,
        "comments": 51,
        "reposts": 27,
        "shares": 0,
        "keyword": "美式復古"
      },
      {
        "permalink": "https://www.threads.com/@spilltheteaandmeal/post/DYmV7D-AIRA",
        "username": "spilltheteaandmeal",
        "post_date": "2026-5-21",
        "content": "想問香港其實有冇自己嘅￼着衫style?\n￼唔係日系韓風個啲喎\n真係港式style個種\n喺網上搵參考好似港風=復古咁",
        "likes": 1619,
        "comments": 319,
        "reposts": 9,
        "shares": 418,
        "keyword": "美式復古"
      },
      {
        "permalink": "https://www.threads.com/@wei_yin_/post/DX4A_Azkn_h",
        "username": "wei_yin_",
        "post_date": "2026-5-3",
        "content": "目前正在尋找不同的室內設計公司想做比較（必須也要擅長軟裝），不知道有沒有人做過類似的風格，能夠推薦你的設計公司/設計師嗎🥺\n喜歡的風格大概是美式自然風跟mid century modern\n不喜歡侘寂感、不喜歡太minimalism 、不喜歡無印風\n喜歡視覺上溫暖、溫馨、柔軟，喜歡胡桃木元素以及少量鐵件元素，必須要非常擅長室內燈光設計\n地點在台北市中心",
        "likes": 204,
        "comments": 31,
        "reposts": 3,
        "shares": 91,
        "keyword": "美式復古"
      },
      {
        "permalink": "https://www.threads.com/@zsro.3/post/DYodtIEFLy-",
        "username": "zsro.3",
        "post_date": "2026-5-22",
        "content": "最近在想要不要燙美式前刺 有推薦的設計師嗎",
        "likes": 13,
        "comments": 15,
        "reposts": 1,
        "shares": 0,
        "keyword": "美式復古"
      },
      {
        "permalink": "https://www.threads.com/@vento_ceilingfan/post/DZHjnavEoJc",
        "username": "vento_ceilingfan",
        "post_date": "1天",
        "content": "你喜歡溫潤原木、藤編的東南亞自然風格，\n還是\n典雅且簡約的美式風格呢?\n或是其他? 跟我們聊聊👋",
        "likes": 3,
        "comments": 0,
        "reposts": 0,
        "shares": 0,
        "keyword": "美式復古"
      },
      {
        "permalink": "https://www.threads.com/@yuetung_ans2dl/post/DZDGqRGkzw5",
        "username": "yuetung_ans2dl",
        "post_date": "3天",
        "content": "阿磪唱美娜的넘넘넘趴特\n超級可愛🥹🥹💖💖💖",
        "likes": 724,
        "comments": 49,
        "reposts": 17,
        "shares": 0,
        "keyword": "阿美咔嘰"
      }
    ]
  }
}