{
  "2026-05-07": {
    "keyword_tags": [
      "男生穿搭",
      "美式復古",
      "阿美咔嘰"
    ],
    "ai_summary": {
      "title": "今日 Threads 穿搭趨勢熱門追蹤",
      "intro": "今日 Threads 穿搭討論集中在「日系慵懶風」與「美式復古色系」兩大核心。日系穿搭因其不挑年齡與高實用性，持續受台灣男性關注；同時，東京原宿、澀谷的實體購物指南也成為熱門內容，反映出實體消費與旅遊穿搭的緊密連結。在復古風格方面，美式復古（Americana）強調色彩與氛圍感的經營，棕紅色調成為本季亮點。此外，針對穿搭新手與預算有限者的店舖清單，依然具備高度的轉發與收藏價值。",
      "highlights": [
        {
          "title": "美式復古氛圍感的色系經營",
          "description": "貼文強調如何拿捏美式復古風，特別提到棕紅色調與環境氛圍的搭配，獲得超過 2.5 萬次點讚，顯示復古美學在社群上極具渲染力。",
          "url": "https://www.threads.com/@nigxa.pro/post/DSnUVzeEwyV"
        },
        {
          "title": "日系少年感的慵懶鬆弛穿搭",
          "description": "推廣台灣男生學習日系風格，強調其不分年齡的百搭性與「慵懶鬆弛感」，在社群引發高度共鳴，獲得 1.2 萬次點讚。",
          "url": "https://www.threads.com/@meizzz1111/post/DWWeKAiEgzl"
        },
        {
          "title": "東京潮流一小時快攻購物指南",
          "description": "專業分析原宿與澀谷的購物路線，涵蓋 Auralee、Beams、Human Made 等高端日潮與機能品牌，並提供都市極簡與 Vintage 風格的精選清單。",
          "url": "https://www.threads.com/@miracle3/post/DVFs1DJEb_m"
        },
        {
          "title": "男生穿搭入門必收店舖清單",
          "description": "針對想改善穿搭但無從下手的男性的實用推薦，整理出五間值得關注的指標性店鋪，適合新手建立個人風格。",
          "url": "https://www.threads.com/@axvioivxa/post/DSvbrAFk4R-"
        },
        {
          "title": "小資穿搭必看的高 CP 值單品",
          "description": "鎖定不想花大錢也能提升質感的客群，分享數款基礎且實搭的必備單品，強調台灣男生的日常實穿需求。",
          "url": "https://www.threads.com/@iamsodope23/post/DXRPrY-Exh_"
        }
      ]
    },
    "posts": [
      {
        "permalink": "https://www.threads.com/@axvioivxa/post/DSvbrAFk4R-",
        "username": "axvioivxa",
        "post_date": "2025-12-26",
        "content": "男生想要改善穿搭不能不知道的五間店🫵",
        "likes": 481,
        "comments": 6,
        "reposts": 64,
        "shares": 230,
        "keyword": "男生穿搭"
      },
      {
        "permalink": "https://www.threads.com/@meizzz1111/post/DWWeKAiEgzl",
        "username": "meizzz1111",
        "post_date": "2026-3-26",
        "content": "瘋掉！台灣男生一定要去學日系少年穿搭！！\n因為不分年齡超百搭～妥妥的慵懶鬆弛感😎",
        "likes": 12000,
        "comments": 733,
        "reposts": 865,
        "shares": 8476,
        "keyword": "男生穿搭"
      },
      {
        "permalink": "https://www.threads.com/@ldddin/post/DMsZophvv4_",
        "username": "ldddin",
        "post_date": "2025-7-29",
        "content": "其實當一個男生很認真健身 讀書 培養自己的興趣 接觸世界 學穿搭 開始保養 開始打理自己 戒掉打電動 充實自己 想說會不會有人注意的時候\n你會發現你還是會輸給那些長比你帥的人",
        "likes": 19000,
        "comments": 640,
        "reposts": 1286,
        "shares": 3190,
        "keyword": "男生穿搭"
      },
      {
        "permalink": "https://www.threads.com/@miracle3/post/DVFs1DJEb_m",
        "username": "miracle3",
        "post_date": "2026-2-23",
        "content": "「快！我只有一小時血拼」原宿/澀谷Google Map私藏分享\n上回稍稍分享自己的私藏東京「掃貨」地圖，想不到蠻有回響\n今次決定為大家度身訂造，一小時血拼快攻指南，用最順暢的路線，盡攬東京潮物！\n原宿篇：\n由東急Plaza為起點，喜歡精緻日潮的向左走，鍾愛機能服就向右走。一條直路，另加小巷內如carol等小店，輕易網羅以下品牌：ssetin, Auralee, beams,United Tokyo, yoke, North Face, Chrome Heart等\n風格：都市極簡/戶外/Vintage\n澀谷篇：\n兩條精選路線，\n1) 從Parco開始，在百貨內橫掃Human Made, Porter, North Face Purple Label, CDG, Homme Issey Miyake。或者向tobu hotel方向直行轉右，一次走遍Beams, Freak’s Store, SHIPS, Hare。還有街頭一點有Stussy, Carhartt WIP。\n2) 留言續..\nGoogle Map路線內，每間店都有詳細介紹，立即追蹤我，並在留言+1，我就會私信給你!",
        "likes": 133,
        "comments": 96,
        "reposts": 17,
        "shares": 161,
        "keyword": "男生穿搭"
      },
      {
        "permalink": "https://www.threads.com/@iamsodope23/post/DXRPrY-Exh_",
        "username": "iamsodope23",
        "post_date": "2026-4-18",
        "content": "台灣男生不想花大錢穿搭\n拜託收藏這幾件就好..",
        "likes": 483,
        "comments": 11,
        "reposts": 32,
        "shares": 285,
        "keyword": "男生穿搭"
      },
      {
        "permalink": "https://www.threads.com/@nigxa.pro/post/DSnUVzeEwyV",
        "username": "nigxa.pro",
        "post_date": "2025-12-23",
        "content": "美式復古風拿捏🤏棕紅色圓角磚太有氛圍感了",
        "likes": 25000,
        "comments": 243,
        "reposts": 1408,
        "shares": 2942,
        "keyword": "美式復古"
      },
      {
        "permalink": "https://www.threads.com/@_esther_hong/post/DX5wVXBEXNr",
        "username": "_esther_hong",
        "post_date": "3天",
        "content": "阿臣突襲903‼️\n森美的女兒也喜歡聽阿臣的沙龍🥰🥰🥰",
        "likes": 1579,
        "comments": 9,
        "reposts": 15,
        "shares": 382,
        "keyword": "阿美咔嘰"
      },
      {
        "permalink": "https://www.threads.com/@chenlin3914/post/DM4NANjxJp2",
        "username": "chenlin3914",
        "post_date": "2025-8-3",
        "content": "這個妹妹真的漂亮\n阿美族的改應❤️",
        "likes": 8693,
        "comments": 120,
        "reposts": 27,
        "shares": 465,
        "keyword": "阿美咔嘰"
      },
      {
        "permalink": "https://www.threads.com/@yuqi_157/post/DKPySfGy5fK",
        "username": "yuqi_157",
        "post_date": "2025-5-29",
        "content": "親愛的 哪裡還讓你拿不出手？\n#阿美族",
        "likes": 1975,
        "comments": 19,
        "reposts": 5,
        "shares": 38,
        "keyword": "阿美咔嘰"
      }
    ]
  },
  "2026-05-06": {
    "keyword_tags": [
      "男生穿搭",
      "美式復古",
      "阿美咔嘰"
    ],
    "ai_summary": {
      "title": "今日 Threads 穿搭熱門追蹤：從韓系簡約到硬派復古的深度對話",
      "intro": "今日 Threads 穿搭社群呈現出極高的專業化與實務性。趨勢主要集中在兩大方向：一是「韓系簡約配色與比例修正」，網友熱衷於討論如何透過配色邏輯與穿衣技巧（如解決五五身比例）提升日常質感；二是「阿美咔嘰（Amekaji）復古風潮」，包含軍事風格復刻、丹寧養褲美學以及手工靴保養，顯示出 Threads 用戶對於具備歷史底蘊與工藝細節的單品有著深厚的興趣與極高的鑑賞力。",
      "highlights": [
        {
          "title": "韓系配色原則：男裝質感的捷徑",
          "description": "此貼文強調掌握韓系男生的配色原則即可達成高分穿搭，獲得超過萬次點讚，反映出廣大用戶對於系統化穿搭邏輯的渴望。",
          "url": "https://www.threads.com/@henryhohoha/post/DSmjafgAbrG"
        },
        {
          "title": "深度分析：Vintage 穿搭與個人氣質的適配性",
          "description": "專業分析如何結合 Vintage 單品與身形優勢，並提及緊身輕亞風與配件（如棒球帽、細手鏈）的畫龍點睛效果，是極具參考價值的風格解析。",
          "url": "https://www.threads.com/@capybara.0303/post/DU8GoPtk1aj"
        },
        {
          "title": "影視連動：阿美咔嘰軍事復刻熱潮",
          "description": "受影集《空戰群英》啟發，網友分享復刻二戰軍事風格的穿著，展現出影視文化對復古潮流（Heritage Style）的強力帶動作用。",
          "url": "https://www.threads.com/@ma_mao_mao/post/DU-i47Jj-8z"
        },
        {
          "title": "丹寧養褲哲學：平價品牌與自然色落",
          "description": "網友分享使用 Wrangler 47mwz 的養褲心得，挑戰「昂貴才是正宗」的迷思，引發關於自然養褲習慣與實用主義的熱烈討論。",
          "url": "https://www.threads.com/@anpanman_m38/post/DWrNtyMj66V"
        },
        {
          "title": "細節控的皮靴保養：RDT Vincent 貼底爭議",
          "description": "針對稀有手工皮靴 Rolling Dub Trio 的新鞋保養討論，觸及了復古玩家對於「原味開穿」與「保護性貼底」的權衡與美學考量。",
          "url": "https://www.threads.com/@wesley_chang/post/DU7ilFpj4Uw"
        }
      ]
    },
    "posts": [
      {
        "permalink": "https://www.threads.com/@henryhohoha/post/DSmjafgAbrG",
        "username": "henryhohoha",
        "post_date": "2025-12-23",
        "content": "男生學穿搭 像韓國男生這樣把握配色原則\n真的起碼80分以上🙂‍↕️",
        "likes": 11000,
        "comments": 169,
        "reposts": 696,
        "shares": 5008,
        "keyword": "男生穿搭"
      },
      {
        "permalink": "https://www.threads.com/@roger_iamreallyfuck/post/DSo3k7zkrDT",
        "username": "roger_iamreallyfuck",
        "post_date": "2025-12-24",
        "content": "我這套直接屌贏你那些2486穿搭",
        "likes": 11000,
        "comments": 35,
        "reposts": 132,
        "shares": 1356,
        "keyword": "男生穿搭"
      },
      {
        "permalink": "https://www.threads.com/@bat.4602100/post/DXUZr3DkW01",
        "username": "bat.4602100",
        "post_date": "2026-4-19",
        "content": "大家好\n想請問一下各位懂穿搭的男生帥哥們🤣\n最近想幫老公改造一下穿衣風格\n才發現他身材比例很不好哈哈\n大概是五五身\n這樣的身材比例要怎麼穿才不會顯得很矮\n我上網查到是說把上衣紮進去褲子裡\n但他也似乎不適合🤣穿起來很好笑\n還有別的方法嗎？\n不然看他永遠只會穿合身牛仔褲上面加一件素t\n先謝謝各位的回覆了🥹",
        "likes": 32,
        "comments": 48,
        "reposts": 3,
        "shares": 0,
        "keyword": "男生穿搭"
      },
      {
        "permalink": "https://www.threads.com/@capybara.0303/post/DU8GoPtk1aj",
        "username": "capybara.0303",
        "post_date": "2026-2-19",
        "content": "我觉得他的穿搭牛逼的点在于虽然看起来不会得风湿 但是仔细看其实装逼得要死 好多买不到买不起的vintage呵呵 穿搭风格和本人气质也相当适配 当然他一定要感谢这个基因彩票 头小肩宽窄腰长腿 174倒三角还有这个腿长真的救大命了 天选裤子圣体 因为小腿又长又细卫衣七分裤只有他穿才有那个感觉 当然最近的紧身轻亚风也是非常带感 穿搭总是乍一看没什么 但大概就是亮色棒球帽 画龙点睛 只露出一边的高帮ro 黑色紧身上衣白色腰带这样子的东西一直在勾引我吧 很难想象他练习生时期对时尚不感兴趣 看他前段时间突然对首饰感兴趣然后戴上了那个骚不拉几的细手链 还有点期待他的时尚之路了 最后有点难能可贵的是他还是个长期主义 我真的看了好久他那个龟壳（x蟒纹）双肩包 不懂为什么有些人觉得他土穿的一般都是造型师搭的 抱歉真的不这么觉得 他穿搭碉堡了甚至对普通人都很有参考价值 意思是其实好看松弛还很实用 还有不想帮那些模仿他风格的筹男起号 带个豆兵戴个new era穿个七分裤就被捧",
        "likes": 513,
        "comments": 44,
        "reposts": 23,
        "shares": 53,
        "keyword": "男生穿搭"
      },
      {
        "permalink": "https://www.threads.com/@dozjj_0915/post/DGG3ox8Tb5m",
        "username": "dozjj_0915",
        "post_date": "2025-2-15",
        "content": "有沒有推薦男生的衣服、褲子賣場\n想買衣服送給男友",
        "likes": 53,
        "comments": 0,
        "reposts": 0,
        "shares": 0,
        "keyword": "男生穿搭"
      },
      {
        "permalink": "https://www.threads.com/@ai_09.29/post/C6IF1D3SMzz",
        "username": "ai_09.29",
        "post_date": "2024-4-24",
        "content": "兩房現代簡約\n上跟下選哪一個",
        "likes": 2873,
        "comments": 466,
        "reposts": 28,
        "shares": 0,
        "keyword": "美式復古"
      },
      {
        "permalink": "https://www.threads.com/@__ying_1126/post/C2FUO-Ov_Ea",
        "username": "__ying_1126",
        "post_date": "2024-1-14",
        "content": "美式穿搭 有人嗎🙋🏻‍♀️",
        "likes": 1071,
        "comments": 9,
        "reposts": 0,
        "shares": 0,
        "keyword": "美式復古"
      },
      {
        "permalink": "https://www.threads.com/@ma_mao_mao/post/DU-i47Jj-8z",
        "username": "ma_mao_mao",
        "post_date": "2026-2-20",
        "content": "在飛24次就可以退伍了😂\n空戰群英超好看，復刻一下裡面的穿著",
        "likes": 1239,
        "comments": 125,
        "reposts": 10,
        "shares": 30,
        "keyword": "阿美咔嘰"
      },
      {
        "permalink": "https://www.threads.com/@zawa.archive/post/DR4gEM1EZN2",
        "username": "zawa.archive",
        "post_date": "2025-12-5",
        "content": "不知道有沒有喜歡阿美咔嘰的玩家，這邊有件來自 bryceland’s 的 type 1 可以參考一下！\nzawa.archive",
        "likes": 49,
        "comments": 3,
        "reposts": 2,
        "shares": 0,
        "keyword": "阿美咔嘰"
      },
      {
        "permalink": "https://www.threads.com/@anpanman_m38/post/DWrNtyMj66V",
        "username": "anpanman_m38",
        "post_date": "2026-4-3",
        "content": "Wrangler 47mwz\n這是一件才40幾塊美金的牛仔褲，以前我也瘋買LVC或是日系品牌一件動輒將近萬元台幣的高價褲，但是自從接觸Wrangler後，我就沒再花大錢買過牛仔褲，現有的牛仔褲有一半是Wrangler再來是Lee，LVC賣到只剩一件55501，只是單純覺得Wrangler好穿，至於色落…我標籤剪掉就直接丟洗衣機，然後可能一兩個禮拜洗一次，沒有刻意要養對比很深的感覺，只是就是照自己的使用習慣去養褲子，第一張是我養的第一件47mwz，對比真的不深，但我覺得很自然不刻意，第二張是我現在每天著用的第二條47mwz，可以看到我的習慣改變了，喜歡把我的iphone11塞在口袋，這件我有刻意大概一個月才丟洗衣機一次，我養的真的沒很厲害，只是單純喜歡依照自己習慣養出來的自然👍 再來就是…我真的很愛Wrangler這個牌子❤️",
        "likes": 81,
        "comments": 23,
        "reposts": 0,
        "shares": 0,
        "keyword": "阿美咔嘰"
      },
      {
        "permalink": "https://www.threads.com/@wesley_chang/post/DU7ilFpj4Uw",
        "username": "wesley_chang",
        "post_date": "2026-2-19",
        "content": "可能是上輩子有燒了好香，沒想到能找到一雙全新的RDT Vincent，媽呀有夠美的！\n不過是第一次穿全皮底的靴子，想問問各位前輩、先進的意見，你們是會再額外貼底還是直接開穿派？\n祝各位新年快樂，工作順利發大財想買什麼靴就有什麼靴！",
        "likes": 106,
        "comments": 50,
        "reposts": 3,
        "shares": 0,
        "keyword": "阿美咔嘰"
      }
    ]
  },
  "2026-05-05": {
    "keyword_tags": [
      "男生穿搭",
      "美式復古",
      "阿美咔嘰"
    ],
    "ai_summary": {
      "title": "今日 Threads 穿搭與復古風格趨勢追蹤",
      "intro": "今日 Threads 上的穿搭討論聚焦於「美式復古」風格的實踐，特別是針對「美式男孩」風格的穿搭邏輯教學。此外，社群對於多樣化小眾風格（如 Y2K、古著、地雷系）的採購渠道表現出強烈的好奇與需求。值得注意的是，復古審美已從服裝本身延伸至生活視覺元素，顯示出一種全方位復古生活態度的流行趨勢。",
      "highlights": [
        {
          "title": "美式男孩復古穿搭教學",
          "description": "由 @chien_0100 分享的美式復古風格教學，針對男孩穿搭提供具體的搭配建議，獲得社群高度關注與認可，成為今日熱度最高的穿搭指引貼文。",
          "url": "https://www.threads.com/@chien_0100/post/DGxWqgHpcES"
        },
        {
          "title": "多樣化穿搭風格購買通路諮詢",
          "description": "網友 @ne_.oxo 針對 Y2K、古著、龐克等多種風格發起求物提問，顯示 Threads 使用者對於建立獨特個人風格與尋找非主流服飾通路有強烈的需求。",
          "url": "https://www.threads.com/@ne_.oxo/post/DRR6U8PknhI"
        },
        {
          "title": "復古審美中的視覺文化觀察",
          "description": "貼文聚焦於街頭復古字體與招牌，雖然非直接穿搭，但反映出熱愛復古穿搭的族群對於復古氛圍（Aesthetic）的全面追求與高度敏感度。",
          "url": "https://www.threads.com/@dobermantoy2024/post/DKuD28lyrYI"
        }
      ]
    },
    "posts": [
      {
        "permalink": "https://www.threads.com/@chien_0100/post/DGxWqgHpcES",
        "username": "chien_0100",
        "post_date": "2025-3-4",
        "content": "教你美式男孩都怎麼穿搭的",
        "likes": 2142,
        "comments": 41,
        "reposts": 165,
        "shares": 423,
        "keyword": "美式復古"
      },
      {
        "permalink": "https://www.threads.com/@y.jason_970120/post/DRPU73skeVV",
        "username": "y.jason_970120",
        "post_date": "2025-11-19",
        "content": "聽說最近很流行日式建築",
        "likes": 323,
        "comments": 6,
        "reposts": 1,
        "shares": 5,
        "keyword": "美式復古"
      },
      {
        "permalink": "https://www.threads.com/@dayoselect/post/DVvJ_n0k8rD",
        "username": "dayoselect",
        "post_date": "2026-3-11",
        "content": "要歐美化了，越來越多人傾向用軟裝，成為家裡的主要風格語言，其他就做到極簡。",
        "likes": 1082,
        "comments": 81,
        "reposts": 14,
        "shares": 418,
        "keyword": "美式復古"
      },
      {
        "permalink": "https://www.threads.com/@dobermantoy2024/post/DKuD28lyrYI",
        "username": "dobermantoy2024",
        "post_date": "2025-6-10",
        "content": "好喜歡這種復古字體的招牌～每次看到都忍不住想拍照📷",
        "likes": 4077,
        "comments": 63,
        "reposts": 113,
        "shares": 49,
        "keyword": "美式復古"
      },
      {
        "permalink": "https://www.threads.com/@ne_.oxo/post/DRR6U8PknhI",
        "username": "ne_.oxo",
        "post_date": "2025-11-20",
        "content": "想問問各位的地雷系 量產 日系 千禧 y2k 美式 龐克 古著 這些風格的衣服都是在哪裡買的😭",
        "likes": 168,
        "comments": 19,
        "reposts": 4,
        "shares": 19,
        "keyword": "美式復古"
      },
      {
        "permalink": "https://www.threads.com/@qqfanquei/post/DGx9MPqTMte",
        "username": "qqfanquei",
        "post_date": "2025-3-4",
        "content": "老師的一份關心\n阿美突然眼眶濕潤\n阿美不孤單\n今天起 增加了很多「阿美」族\n@wanghongwei2025gg",
        "likes": 7790,
        "comments": 89,
        "reposts": 491,
        "shares": 122,
        "keyword": "阿美咔嘰"
      },
      {
        "permalink": "https://www.threads.com/@xuan_150727/post/DMyuHnoSEfV",
        "username": "xuan_150727",
        "post_date": "2025-8-1",
        "content": "20250801\n📍原名日📍\n今年我的身分不一樣了❤️\n正式成為 阿美少女 🤣🥰\n#捌月壹日 #原民日\n#正式成為阿美女孩👧\n#原住民的孩子❤️\n#我是原住民我驕傲👍\n#Alomi💋 #amis🧡\n#文化創意園區",
        "likes": 585,
        "comments": 13,
        "reposts": 2,
        "shares": 0,
        "keyword": "阿美咔嘰"
      },
      {
        "permalink": "https://www.threads.com/@_ihsin.c/post/DM5ZlsqvQ56",
        "username": "_ihsin.c",
        "post_date": "2025-8-3",
        "content": "到底為什麼阿咪被指的時候愛炸毛",
        "likes": 5745,
        "comments": 73,
        "reposts": 170,
        "shares": 422,
        "keyword": "阿美咔嘰"
      }
    ]
  },
  "2026-05-04": {
    "keyword_tags": [
      "男生穿搭",
      "美式復古",
      "阿美咔嘰"
    ],
    "ai_summary": {
      "title": "今日 Threads 穿搭趨勢報告：夏日男生教科書與復古美學再起",
      "intro": "今日 Threads 社群對於穿搭的討論高度集中在『男生夏日造型』與『高品質復古感』兩大核心。數據顯示，具有『教科書等級』的穿搭範本獲得了最高互動率，反映出使用者對於實際搭配靈感的強烈渴求。此外，社群對於過度單一化（複製貼上）的日系穿搭出現了反思，而高品質的美式復古造型則持續佔據流量高地。",
      "highlights": [
        {
          "title": "男生穿搭教科書：萬人點讚的夏日範本",
          "description": "貼文由 @_hyggexx 發布，被稱為帥一整夏的男人，獲得高達 2.7 萬個讚，顯示出簡潔且具質感的男生夏日穿搭最能引起大眾共鳴。",
          "url": "https://www.threads.com/@_hyggexx/post/DECzU6ZSfOr"
        },
        {
          "title": "美式復古造形展現：質感男性的魅力關鍵",
          "description": "帳號 @the_brighton_knight 分享了精心打理的復古造型，憑藉其強烈的風格感獲得 2 萬次點讚，證明復古時尚仍是 Threads 上的流量密碼。",
          "url": "https://www.threads.com/@the_brighton_knight/post/DSK7CDMEiey"
        },
        {
          "title": "夏日穿搭集思廣益：社群互助式穿搭需求",
          "description": "由 @_djie48.c 徵集男生夏季穿搭照，引發超過 5,000 名網友熱烈響應與分享，反映出男性使用者在夏季更換造型時的高度焦慮與求知欲。",
          "url": "https://www.threads.com/@_djie48.c/post/DHqvvFDB3Jq"
        },
        {
          "title": "穿搭風格的反思：打破日系穿搭複製化",
          "description": "貼文 @ieeee233 針對大眾認知中『日男很會穿』的觀念提出反思，討論造型趨同現象，獲得超過千次按讚與討論，展現出對獨特風格的追求。",
          "url": "https://www.threads.com/@ieeee233/post/DXTusPvAdMz"
        }
      ]
    },
    "posts": [
      {
        "permalink": "https://www.threads.com/@_hyggexx/post/DECzU6ZSfOr",
        "username": "_hyggexx",
        "post_date": "2024-12-26",
        "content": "男生穿搭教科書🈶\n帥了我一整個夏天的男人😍",
        "likes": 27000,
        "comments": 316,
        "reposts": 1224,
        "shares": 2820,
        "keyword": "男生穿搭"
      },
      {
        "permalink": "https://www.threads.com/@_kartalin/post/DWo6zqMj179",
        "username": "_kartalin",
        "post_date": "2026-4-2",
        "content": "最近又想要爆買衣服 請各位推薦你們覺得好看的男裝！",
        "likes": 42,
        "comments": 35,
        "reposts": 5,
        "shares": 0,
        "keyword": "男生穿搭"
      },
      {
        "permalink": "https://www.threads.com/@_djie48.c/post/DHqvvFDB3Jq",
        "username": "_djie48.c",
        "post_date": "2025-3-26",
        "content": "徵求男生夏季穿搭照片，借我參考拜託了😭",
        "likes": 5350,
        "comments": 555,
        "reposts": 143,
        "shares": 774,
        "keyword": "男生穿搭"
      },
      {
        "permalink": "https://www.threads.com/@ieeee233/post/DXTusPvAdMz",
        "username": "ieeee233",
        "post_date": "2026-4-19",
        "content": "不是说日男都很会穿搭吗 怎么得能家复制粘贴出两个这样的",
        "likes": 1396,
        "comments": 19,
        "reposts": 29,
        "shares": 143,
        "keyword": "男生穿搭"
      },
      {
        "permalink": "https://www.threads.com/@hokkaido161373/post/DXQ3zkmlPe8",
        "username": "hokkaido161373",
        "post_date": "2026-4-18",
        "content": "各位男生，有沒有春夏穿搭？\n麻煩曬一下你們的モテ服讓我參考學習一下。\nモテ服:指受歡迎討喜穿搭、讓人有好感的服裝",
        "likes": 55,
        "comments": 46,
        "reposts": 11,
        "shares": 0,
        "keyword": "男生穿搭"
      },
      {
        "permalink": "https://www.threads.com/@megahoshi.wxy/post/DLhYchxzmpJ",
        "username": "megahoshi.wxy",
        "post_date": "2025-6-30",
        "content": "ㄧ年來似顏繪風格的演進🎨",
        "likes": 9274,
        "comments": 189,
        "reposts": 264,
        "shares": 214,
        "keyword": "美式復古"
      },
      {
        "permalink": "https://www.threads.com/@madellynnine/post/DM4xyUrT97Y",
        "username": "madellynnine",
        "post_date": "2025-8-3",
        "content": "東區的美式復古拍貼📷",
        "likes": 236,
        "comments": 4,
        "reposts": 124,
        "shares": 0,
        "keyword": "美式復古"
      },
      {
        "permalink": "https://www.threads.com/@the_brighton_knight/post/DSK7CDMEiey",
        "username": "the_brighton_knight",
        "post_date": "2025-12-12",
        "content": "造型弄得比較復古",
        "likes": 20000,
        "comments": 259,
        "reposts": 173,
        "shares": 239,
        "keyword": "美式復古"
      },
      {
        "permalink": "https://www.threads.com/@wei_yin_/post/DX4A_Azkn_h",
        "username": "wei_yin_",
        "post_date": "16小時",
        "content": "目前正在尋找不同的室內設計公司想做比較（必須也要擅長軟裝），不知道有沒有人做過類似的風格，能夠推薦你的設計公司/設計師嗎🥺\n喜歡的風格大概是美式自然風跟mid century modern\n不喜歡侘寂感、不喜歡太minimalism 、不喜歡無印風\n喜歡視覺上溫暖、溫馨、柔軟，喜歡胡桃木元素以及少量鐵件元素，必須要非常擅長室內燈光設計\n地點在台北市中心",
        "likes": 79,
        "comments": 17,
        "reposts": 24,
        "shares": 0,
        "keyword": "美式復古"
      },
      {
        "permalink": "https://www.threads.com/@changche.drawing/post/DMZ6ELQR6lO",
        "username": "changche.drawing",
        "post_date": "2025-7-22",
        "content": "以家具來說，台灣的風格是自由、靈活、幽默ㄅ。",
        "likes": 2727,
        "comments": 21,
        "reposts": 194,
        "shares": 61,
        "keyword": "美式復古"
      },
      {
        "permalink": "https://www.threads.com/@btssu.ga0309/post/DXB9I6mkZLd",
        "username": "btssu.ga0309",
        "post_date": "2026-4-12",
        "content": "阿米舉著‘拜託Come Over音源上架吧’\n被官方拍到了 切拜🙏😭",
        "likes": 13000,
        "comments": 11,
        "reposts": 577,
        "shares": 155,
        "keyword": "阿美咔嘰"
      },
      {
        "permalink": "https://www.threads.com/@0m1muoy/post/C9crwglvAi_",
        "username": "0m1muoy",
        "post_date": "2024-7-15",
        "content": "花蓮玉里阿美旋\n.\n.\n.\n只是學一下現在大家都在發的🤣",
        "likes": 1517,
        "comments": 63,
        "reposts": 2,
        "shares": 16,
        "keyword": "阿美咔嘰"
      },
      {
        "permalink": "https://www.threads.com/@pllifish/post/DXyPrPVAJYr",
        "username": "pllifish",
        "post_date": "2天",
        "content": "台中安美大娃剩下架上這些",
        "likes": 323,
        "comments": 12,
        "reposts": 1,
        "shares": 77,
        "keyword": "阿美咔嘰"
      },
      {
        "permalink": "https://www.threads.com/@naush.eh/post/DXo-k6Mkm-W",
        "username": "naush.eh",
        "post_date": "6天",
        "content": "阿姆 我有可愛侵略症",
        "likes": 38000,
        "comments": 265,
        "reposts": 536,
        "shares": 898,
        "keyword": "阿美咔嘰"
      },
      {
        "permalink": "https://www.threads.com/@a_168_88/post/DXWZxn6mdVQ",
        "username": "a_168_88",
        "post_date": "2026-4-20",
        "content": "高火安美進新娃了\nSumimi初華Get!\n我看裡面還有阿拉蕾\n甜甜圈女士也有🍩",
        "likes": 377,
        "comments": 31,
        "reposts": 9,
        "shares": 168,
        "keyword": "阿美咔嘰"
      }
    ]
  },
  "2026-05-03": {
    "keyword_tags": [
      "男生穿搭",
      "美式復古",
      "阿美咔嘰"
    ],
    "ai_summary": {
      "title": "今日 Threads 穿搭趨勢熱門追蹤：韓系純慾風與美式復古的穿搭辯論",
      "intro": "今日 Threads 的時尚討論集中於「男生穿搭的定義」與「體態對風格的影響」。男裝方面，網友高度關注如何從單調的全黑穿搭轉向更具層次感的韓系風格；美式復古風格則展現出強烈的採購需求，特別是帶有圖騰與文字的基礎款單品。此外，社群中也出現關於『穿搭精髓在於體態』的熱議，反映出使用者對於風格與身形比例的高度敏感。",
      "highlights": [
        {
          "title": "韓系『純慾風』男裝成熱點",
          "description": "貼文指出韓劇風格的乾淨、具備層次感的穿搭被視為男生的『純慾風』，引發大量女性受眾共鳴與男性對穿搭細節的探討。",
          "url": "https://www.threads.com/@twwz_df/post/DTDMZNqkkeq"
        },
        {
          "title": "穿搭風格的殘酷真相：體態論",
          "description": "一則關於韓、日、美、法式穿搭精髓在於『薄薄一片人』的貼文獲得極高讚數，顯示社群普遍認同身形與穿搭效果的連結。",
          "url": "https://www.threads.com/@xwwxz_1221/post/DWLmiYzFYj4"
        },
        {
          "title": "打破全黑迷思的穿搭提問",
          "description": "許多男性用戶開始反思『全黑穿搭』是否等於『會穿搭』，並針對顏色搭配與具備何種資格才算懂時尚展開熱烈討論。",
          "url": "https://www.threads.com/@___7en18/post/CzskyMey4MV"
        },
        {
          "title": "美式基礎款圖騰單品需求上升",
          "description": "美式復古愛好者開始尋求超越「素面 T-shirt」的基礎單品，特別是帶有文字或特定圖案設計的款式，顯示分眾市場的細分化。",
          "url": "https://www.threads.com/@17zzzzzzzz_/post/DW_j1jcD_zw"
        },
        {
          "title": "線下實體店鋪資訊求助熱潮",
          "description": "針對特定風格（如美式復古）的雙北實體店鋪導引需求增加，顯示 Threads 已成為穿搭愛好者交換實體購物資源的重要情報站。",
          "url": "https://www.threads.com/@ieeeei_ii_8/post/DXdc36Ykbtq"
        }
      ]
    },
    "posts": [
      {
        "permalink": "https://www.threads.com/@_1oone/post/DTfKenZk_xU",
        "username": "_1oone",
        "post_date": "2026-1-14",
        "content": "好奇男生怎樣才有資格叫做會穿搭",
        "likes": 428,
        "comments": 101,
        "reposts": 2,
        "shares": 23,
        "keyword": "男生穿搭"
      },
      {
        "permalink": "https://www.threads.com/@twwz_df/post/DTDMZNqkkeq",
        "username": "twwz_df",
        "post_date": "2026-1-3",
        "content": "這根本男生的純慾裝吧！\n男生這樣穿超帥的\n以為是從韓劇走出來的🤣\n今天朋友穿這樣 我說穿這麼帥是要幹嘛🤣\n他說隨便穿捏😱\n我大問號❓有什麼該注意的嗎❓",
        "likes": 830,
        "comments": 8,
        "reposts": 16,
        "shares": 174,
        "keyword": "男生穿搭"
      },
      {
        "permalink": "https://www.threads.com/@___7en18/post/CzskyMey4MV",
        "username": "___7en18",
        "post_date": "2023-11-16",
        "content": "所以男生怎樣的穿搭才是好看的\n顏色搭配還是什麼鬼\n我衣服全部都黑色的==",
        "likes": 838,
        "comments": 64,
        "reposts": 3,
        "shares": 0,
        "keyword": "男生穿搭"
      },
      {
        "permalink": "https://www.threads.com/@xwwxz_1221/post/DWLmiYzFYj4",
        "username": "xwwxz_1221",
        "post_date": "2026-3-22",
        "content": "其实韩式日式美式法式穿搭精髓都是薄薄一片人😭😭😭😭",
        "likes": 7406,
        "comments": 43,
        "reposts": 393,
        "shares": 147,
        "keyword": "美式復古"
      },
      {
        "permalink": "https://www.threads.com/@ciiwppo/post/DUWEAIwk0Ik",
        "username": "ciiwppo",
        "post_date": "2026-2-4",
        "content": "大家都搞美式穿搭 美式妝容 只有我堅持我的美式作息。",
        "likes": 30000,
        "comments": 46,
        "reposts": 4626,
        "shares": 2389,
        "keyword": "美式復古"
      },
      {
        "permalink": "https://www.threads.com/@17zzzzzzzz_/post/DW_j1jcD_zw",
        "username": "17zzzzzzzz_",
        "post_date": "2026-4-11",
        "content": "誰有賣那種比較美式風格的衣服😭\n最近很缺那種一般基礎款的短袖\n但上面有文字 圖案等等的\n不要只有素踢的那種\n其他美式服裝也看看😚",
        "likes": 185,
        "comments": 54,
        "reposts": 4,
        "shares": 60,
        "keyword": "美式復古"
      },
      {
        "permalink": "https://www.threads.com/@ziunaye/post/DMky2lPTdrX",
        "username": "ziunaye",
        "post_date": "2025-7-26",
        "content": "帥吧 新風格",
        "likes": 18000,
        "comments": 73,
        "reposts": 285,
        "shares": 700,
        "keyword": "美式復古"
      },
      {
        "permalink": "https://www.threads.com/@ieeeei_ii_8/post/DXdc36Ykbtq",
        "username": "ieeeei_ii_8",
        "post_date": "2026-4-23",
        "content": "雙北哪裡有這種風格ㄉ衣服呀\n救救我(T_T)",
        "likes": 2207,
        "comments": 52,
        "reposts": 145,
        "shares": 411,
        "keyword": "美式復古"
      },
      {
        "permalink": "https://www.threads.com/@kacaw.kaokoy.cikatopay/post/DU9xKkSACWT",
        "username": "kacaw.kaokoy.cikatopay",
        "post_date": "2026-2-20",
        "content": "阿美族的穿衣敏感度\n#阿美族",
        "likes": 4725,
        "comments": 125,
        "reposts": 90,
        "shares": 149,
        "keyword": "阿美咔嘰"
      },
      {
        "permalink": "https://www.threads.com/@77.linnaa_/post/DSpneNPEq4c",
        "username": "77.linnaa_",
        "post_date": "2025-12-24",
        "content": "安美有PLAVE 卡包跟娃專了😳",
        "likes": 16,
        "comments": 0,
        "reposts": 0,
        "shares": 0,
        "keyword": "阿美咔嘰"
      },
      {
        "permalink": "https://www.threads.com/@girl98818vip/post/C-w5isHPBZw",
        "username": "girl98818vip",
        "post_date": "2024-8-17",
        "content": "久違的服裝😂\n花蓮 阿美❤️",
        "likes": 122,
        "comments": 0,
        "reposts": 0,
        "shares": 0,
        "keyword": "阿美咔嘰"
      },
      {
        "permalink": "https://www.threads.com/@milktea.milktea.351/post/DL9wVgRSUwN",
        "username": "milktea.milktea.351",
        "post_date": "2025-7-11",
        "content": "我阿美族\n你們呢",
        "likes": 1290,
        "comments": 26,
        "reposts": 6,
        "shares": 35,
        "keyword": "阿美咔嘰"
      }
    ]
  }
}