{
  "2026-05-05": {
    "keyword_tags": [
      "男生穿搭",
      "美式復古",
      "阿美咔嘰"
    ],
    "ai_summary": {
      "title": "今日 Threads 穿搭與復古風格趨勢追蹤",
      "intro": "今日 Threads 上的穿搭討論聚焦於「美式復古」風格的實踐，特別是針對「美式男孩」風格的穿搭邏輯教學。此外，社群對於多樣化小眾風格（如 Y2K、古著、地雷系）的採購渠道表現出強烈的好奇與需求。值得注意的是，復古審美已從服裝本身延伸至生活視覺元素，顯示出一種全方位復古生活態度的流行趨勢。",
      "highlights": [
        {
          "title": "美式男孩復古穿搭教學",
          "description": "由 @chien_0100 分享的美式復古風格教學，針對男孩穿搭提供具體的搭配建議，獲得社群高度關注與認可，成為今日熱度最高的穿搭指引貼文。",
          "url": "https://www.threads.com/@chien_0100/post/DGxWqgHpcES"
        },
        {
          "title": "多樣化穿搭風格購買通路諮詢",
          "description": "網友 @ne_.oxo 針對 Y2K、古著、龐克等多種風格發起求物提問，顯示 Threads 使用者對於建立獨特個人風格與尋找非主流服飾通路有強烈的需求。",
          "url": "https://www.threads.com/@ne_.oxo/post/DRR6U8PknhI"
        },
        {
          "title": "復古審美中的視覺文化觀察",
          "description": "貼文聚焦於街頭復古字體與招牌，雖然非直接穿搭，但反映出熱愛復古穿搭的族群對於復古氛圍（Aesthetic）的全面追求與高度敏感度。",
          "url": "https://www.threads.com/@dobermantoy2024/post/DKuD28lyrYI"
        }
      ]
    },
    "posts": [
      {
        "permalink": "https://www.threads.com/@chien_0100/post/DGxWqgHpcES",
        "username": "chien_0100",
        "post_date": "2025-3-4",
        "content": "教你美式男孩都怎麼穿搭的",
        "likes": 2142,
        "comments": 41,
        "reposts": 165,
        "shares": 423,
        "keyword": "美式復古"
      },
      {
        "permalink": "https://www.threads.com/@y.jason_970120/post/DRPU73skeVV",
        "username": "y.jason_970120",
        "post_date": "2025-11-19",
        "content": "聽說最近很流行日式建築",
        "likes": 323,
        "comments": 6,
        "reposts": 1,
        "shares": 5,
        "keyword": "美式復古"
      },
      {
        "permalink": "https://www.threads.com/@dayoselect/post/DVvJ_n0k8rD",
        "username": "dayoselect",
        "post_date": "2026-3-11",
        "content": "要歐美化了，越來越多人傾向用軟裝，成為家裡的主要風格語言，其他就做到極簡。",
        "likes": 1082,
        "comments": 81,
        "reposts": 14,
        "shares": 418,
        "keyword": "美式復古"
      },
      {
        "permalink": "https://www.threads.com/@dobermantoy2024/post/DKuD28lyrYI",
        "username": "dobermantoy2024",
        "post_date": "2025-6-10",
        "content": "好喜歡這種復古字體的招牌～每次看到都忍不住想拍照📷",
        "likes": 4077,
        "comments": 63,
        "reposts": 113,
        "shares": 49,
        "keyword": "美式復古"
      },
      {
        "permalink": "https://www.threads.com/@ne_.oxo/post/DRR6U8PknhI",
        "username": "ne_.oxo",
        "post_date": "2025-11-20",
        "content": "想問問各位的地雷系 量產 日系 千禧 y2k 美式 龐克 古著 這些風格的衣服都是在哪裡買的😭",
        "likes": 168,
        "comments": 19,
        "reposts": 4,
        "shares": 19,
        "keyword": "美式復古"
      },
      {
        "permalink": "https://www.threads.com/@qqfanquei/post/DGx9MPqTMte",
        "username": "qqfanquei",
        "post_date": "2025-3-4",
        "content": "老師的一份關心\n阿美突然眼眶濕潤\n阿美不孤單\n今天起 增加了很多「阿美」族\n@wanghongwei2025gg",
        "likes": 7790,
        "comments": 89,
        "reposts": 491,
        "shares": 122,
        "keyword": "阿美咔嘰"
      },
      {
        "permalink": "https://www.threads.com/@xuan_150727/post/DMyuHnoSEfV",
        "username": "xuan_150727",
        "post_date": "2025-8-1",
        "content": "20250801\n📍原名日📍\n今年我的身分不一樣了❤️\n正式成為 阿美少女 🤣🥰\n#捌月壹日 #原民日\n#正式成為阿美女孩👧\n#原住民的孩子❤️\n#我是原住民我驕傲👍\n#Alomi💋 #amis🧡\n#文化創意園區",
        "likes": 585,
        "comments": 13,
        "reposts": 2,
        "shares": 0,
        "keyword": "阿美咔嘰"
      },
      {
        "permalink": "https://www.threads.com/@_ihsin.c/post/DM5ZlsqvQ56",
        "username": "_ihsin.c",
        "post_date": "2025-8-3",
        "content": "到底為什麼阿咪被指的時候愛炸毛",
        "likes": 5745,
        "comments": 73,
        "reposts": 170,
        "shares": 422,
        "keyword": "阿美咔嘰"
      }
    ]
  },
  "2026-05-04": {
    "keyword_tags": [
      "男生穿搭",
      "美式復古",
      "阿美咔嘰"
    ],
    "ai_summary": {
      "title": "今日 Threads 穿搭趨勢報告：夏日男生教科書與復古美學再起",
      "intro": "今日 Threads 社群對於穿搭的討論高度集中在『男生夏日造型』與『高品質復古感』兩大核心。數據顯示，具有『教科書等級』的穿搭範本獲得了最高互動率，反映出使用者對於實際搭配靈感的強烈渴求。此外，社群對於過度單一化（複製貼上）的日系穿搭出現了反思，而高品質的美式復古造型則持續佔據流量高地。",
      "highlights": [
        {
          "title": "男生穿搭教科書：萬人點讚的夏日範本",
          "description": "貼文由 @_hyggexx 發布，被稱為帥一整夏的男人，獲得高達 2.7 萬個讚，顯示出簡潔且具質感的男生夏日穿搭最能引起大眾共鳴。",
          "url": "https://www.threads.com/@_hyggexx/post/DECzU6ZSfOr"
        },
        {
          "title": "美式復古造形展現：質感男性的魅力關鍵",
          "description": "帳號 @the_brighton_knight 分享了精心打理的復古造型，憑藉其強烈的風格感獲得 2 萬次點讚，證明復古時尚仍是 Threads 上的流量密碼。",
          "url": "https://www.threads.com/@the_brighton_knight/post/DSK7CDMEiey"
        },
        {
          "title": "夏日穿搭集思廣益：社群互助式穿搭需求",
          "description": "由 @_djie48.c 徵集男生夏季穿搭照，引發超過 5,000 名網友熱烈響應與分享，反映出男性使用者在夏季更換造型時的高度焦慮與求知欲。",
          "url": "https://www.threads.com/@_djie48.c/post/DHqvvFDB3Jq"
        },
        {
          "title": "穿搭風格的反思：打破日系穿搭複製化",
          "description": "貼文 @ieeee233 針對大眾認知中『日男很會穿』的觀念提出反思，討論造型趨同現象，獲得超過千次按讚與討論，展現出對獨特風格的追求。",
          "url": "https://www.threads.com/@ieeee233/post/DXTusPvAdMz"
        }
      ]
    },
    "posts": [
      {
        "permalink": "https://www.threads.com/@_hyggexx/post/DECzU6ZSfOr",
        "username": "_hyggexx",
        "post_date": "2024-12-26",
        "content": "男生穿搭教科書🈶\n帥了我一整個夏天的男人😍",
        "likes": 27000,
        "comments": 316,
        "reposts": 1224,
        "shares": 2820,
        "keyword": "男生穿搭"
      },
      {
        "permalink": "https://www.threads.com/@_kartalin/post/DWo6zqMj179",
        "username": "_kartalin",
        "post_date": "2026-4-2",
        "content": "最近又想要爆買衣服 請各位推薦你們覺得好看的男裝！",
        "likes": 42,
        "comments": 35,
        "reposts": 5,
        "shares": 0,
        "keyword": "男生穿搭"
      },
      {
        "permalink": "https://www.threads.com/@_djie48.c/post/DHqvvFDB3Jq",
        "username": "_djie48.c",
        "post_date": "2025-3-26",
        "content": "徵求男生夏季穿搭照片，借我參考拜託了😭",
        "likes": 5350,
        "comments": 555,
        "reposts": 143,
        "shares": 774,
        "keyword": "男生穿搭"
      },
      {
        "permalink": "https://www.threads.com/@ieeee233/post/DXTusPvAdMz",
        "username": "ieeee233",
        "post_date": "2026-4-19",
        "content": "不是说日男都很会穿搭吗 怎么得能家复制粘贴出两个这样的",
        "likes": 1396,
        "comments": 19,
        "reposts": 29,
        "shares": 143,
        "keyword": "男生穿搭"
      },
      {
        "permalink": "https://www.threads.com/@hokkaido161373/post/DXQ3zkmlPe8",
        "username": "hokkaido161373",
        "post_date": "2026-4-18",
        "content": "各位男生，有沒有春夏穿搭？\n麻煩曬一下你們的モテ服讓我參考學習一下。\nモテ服:指受歡迎討喜穿搭、讓人有好感的服裝",
        "likes": 55,
        "comments": 46,
        "reposts": 11,
        "shares": 0,
        "keyword": "男生穿搭"
      },
      {
        "permalink": "https://www.threads.com/@megahoshi.wxy/post/DLhYchxzmpJ",
        "username": "megahoshi.wxy",
        "post_date": "2025-6-30",
        "content": "ㄧ年來似顏繪風格的演進🎨",
        "likes": 9274,
        "comments": 189,
        "reposts": 264,
        "shares": 214,
        "keyword": "美式復古"
      },
      {
        "permalink": "https://www.threads.com/@madellynnine/post/DM4xyUrT97Y",
        "username": "madellynnine",
        "post_date": "2025-8-3",
        "content": "東區的美式復古拍貼📷",
        "likes": 236,
        "comments": 4,
        "reposts": 124,
        "shares": 0,
        "keyword": "美式復古"
      },
      {
        "permalink": "https://www.threads.com/@the_brighton_knight/post/DSK7CDMEiey",
        "username": "the_brighton_knight",
        "post_date": "2025-12-12",
        "content": "造型弄得比較復古",
        "likes": 20000,
        "comments": 259,
        "reposts": 173,
        "shares": 239,
        "keyword": "美式復古"
      },
      {
        "permalink": "https://www.threads.com/@wei_yin_/post/DX4A_Azkn_h",
        "username": "wei_yin_",
        "post_date": "16小時",
        "content": "目前正在尋找不同的室內設計公司想做比較（必須也要擅長軟裝），不知道有沒有人做過類似的風格，能夠推薦你的設計公司/設計師嗎🥺\n喜歡的風格大概是美式自然風跟mid century modern\n不喜歡侘寂感、不喜歡太minimalism 、不喜歡無印風\n喜歡視覺上溫暖、溫馨、柔軟，喜歡胡桃木元素以及少量鐵件元素，必須要非常擅長室內燈光設計\n地點在台北市中心",
        "likes": 79,
        "comments": 17,
        "reposts": 24,
        "shares": 0,
        "keyword": "美式復古"
      },
      {
        "permalink": "https://www.threads.com/@changche.drawing/post/DMZ6ELQR6lO",
        "username": "changche.drawing",
        "post_date": "2025-7-22",
        "content": "以家具來說，台灣的風格是自由、靈活、幽默ㄅ。",
        "likes": 2727,
        "comments": 21,
        "reposts": 194,
        "shares": 61,
        "keyword": "美式復古"
      },
      {
        "permalink": "https://www.threads.com/@btssu.ga0309/post/DXB9I6mkZLd",
        "username": "btssu.ga0309",
        "post_date": "2026-4-12",
        "content": "阿米舉著‘拜託Come Over音源上架吧’\n被官方拍到了 切拜🙏😭",
        "likes": 13000,
        "comments": 11,
        "reposts": 577,
        "shares": 155,
        "keyword": "阿美咔嘰"
      },
      {
        "permalink": "https://www.threads.com/@0m1muoy/post/C9crwglvAi_",
        "username": "0m1muoy",
        "post_date": "2024-7-15",
        "content": "花蓮玉里阿美旋\n.\n.\n.\n只是學一下現在大家都在發的🤣",
        "likes": 1517,
        "comments": 63,
        "reposts": 2,
        "shares": 16,
        "keyword": "阿美咔嘰"
      },
      {
        "permalink": "https://www.threads.com/@pllifish/post/DXyPrPVAJYr",
        "username": "pllifish",
        "post_date": "2天",
        "content": "台中安美大娃剩下架上這些",
        "likes": 323,
        "comments": 12,
        "reposts": 1,
        "shares": 77,
        "keyword": "阿美咔嘰"
      },
      {
        "permalink": "https://www.threads.com/@naush.eh/post/DXo-k6Mkm-W",
        "username": "naush.eh",
        "post_date": "6天",
        "content": "阿姆 我有可愛侵略症",
        "likes": 38000,
        "comments": 265,
        "reposts": 536,
        "shares": 898,
        "keyword": "阿美咔嘰"
      },
      {
        "permalink": "https://www.threads.com/@a_168_88/post/DXWZxn6mdVQ",
        "username": "a_168_88",
        "post_date": "2026-4-20",
        "content": "高火安美進新娃了\nSumimi初華Get!\n我看裡面還有阿拉蕾\n甜甜圈女士也有🍩",
        "likes": 377,
        "comments": 31,
        "reposts": 9,
        "shares": 168,
        "keyword": "阿美咔嘰"
      }
    ]
  },
  "2026-05-03": {
    "keyword_tags": [
      "男生穿搭",
      "美式復古",
      "阿美咔嘰"
    ],
    "ai_summary": {
      "title": "今日 Threads 穿搭趨勢熱門追蹤：韓系純慾風與美式復古的穿搭辯論",
      "intro": "今日 Threads 的時尚討論集中於「男生穿搭的定義」與「體態對風格的影響」。男裝方面，網友高度關注如何從單調的全黑穿搭轉向更具層次感的韓系風格；美式復古風格則展現出強烈的採購需求，特別是帶有圖騰與文字的基礎款單品。此外，社群中也出現關於『穿搭精髓在於體態』的熱議，反映出使用者對於風格與身形比例的高度敏感。",
      "highlights": [
        {
          "title": "韓系『純慾風』男裝成熱點",
          "description": "貼文指出韓劇風格的乾淨、具備層次感的穿搭被視為男生的『純慾風』，引發大量女性受眾共鳴與男性對穿搭細節的探討。",
          "url": "https://www.threads.com/@twwz_df/post/DTDMZNqkkeq"
        },
        {
          "title": "穿搭風格的殘酷真相：體態論",
          "description": "一則關於韓、日、美、法式穿搭精髓在於『薄薄一片人』的貼文獲得極高讚數，顯示社群普遍認同身形與穿搭效果的連結。",
          "url": "https://www.threads.com/@xwwxz_1221/post/DWLmiYzFYj4"
        },
        {
          "title": "打破全黑迷思的穿搭提問",
          "description": "許多男性用戶開始反思『全黑穿搭』是否等於『會穿搭』，並針對顏色搭配與具備何種資格才算懂時尚展開熱烈討論。",
          "url": "https://www.threads.com/@___7en18/post/CzskyMey4MV"
        },
        {
          "title": "美式基礎款圖騰單品需求上升",
          "description": "美式復古愛好者開始尋求超越「素面 T-shirt」的基礎單品，特別是帶有文字或特定圖案設計的款式，顯示分眾市場的細分化。",
          "url": "https://www.threads.com/@17zzzzzzzz_/post/DW_j1jcD_zw"
        },
        {
          "title": "線下實體店鋪資訊求助熱潮",
          "description": "針對特定風格（如美式復古）的雙北實體店鋪導引需求增加，顯示 Threads 已成為穿搭愛好者交換實體購物資源的重要情報站。",
          "url": "https://www.threads.com/@ieeeei_ii_8/post/DXdc36Ykbtq"
        }
      ]
    },
    "posts": [
      {
        "permalink": "https://www.threads.com/@_1oone/post/DTfKenZk_xU",
        "username": "_1oone",
        "post_date": "2026-1-14",
        "content": "好奇男生怎樣才有資格叫做會穿搭",
        "likes": 428,
        "comments": 101,
        "reposts": 2,
        "shares": 23,
        "keyword": "男生穿搭"
      },
      {
        "permalink": "https://www.threads.com/@twwz_df/post/DTDMZNqkkeq",
        "username": "twwz_df",
        "post_date": "2026-1-3",
        "content": "這根本男生的純慾裝吧！\n男生這樣穿超帥的\n以為是從韓劇走出來的🤣\n今天朋友穿這樣 我說穿這麼帥是要幹嘛🤣\n他說隨便穿捏😱\n我大問號❓有什麼該注意的嗎❓",
        "likes": 830,
        "comments": 8,
        "reposts": 16,
        "shares": 174,
        "keyword": "男生穿搭"
      },
      {
        "permalink": "https://www.threads.com/@___7en18/post/CzskyMey4MV",
        "username": "___7en18",
        "post_date": "2023-11-16",
        "content": "所以男生怎樣的穿搭才是好看的\n顏色搭配還是什麼鬼\n我衣服全部都黑色的==",
        "likes": 838,
        "comments": 64,
        "reposts": 3,
        "shares": 0,
        "keyword": "男生穿搭"
      },
      {
        "permalink": "https://www.threads.com/@xwwxz_1221/post/DWLmiYzFYj4",
        "username": "xwwxz_1221",
        "post_date": "2026-3-22",
        "content": "其实韩式日式美式法式穿搭精髓都是薄薄一片人😭😭😭😭",
        "likes": 7406,
        "comments": 43,
        "reposts": 393,
        "shares": 147,
        "keyword": "美式復古"
      },
      {
        "permalink": "https://www.threads.com/@ciiwppo/post/DUWEAIwk0Ik",
        "username": "ciiwppo",
        "post_date": "2026-2-4",
        "content": "大家都搞美式穿搭 美式妝容 只有我堅持我的美式作息。",
        "likes": 30000,
        "comments": 46,
        "reposts": 4626,
        "shares": 2389,
        "keyword": "美式復古"
      },
      {
        "permalink": "https://www.threads.com/@17zzzzzzzz_/post/DW_j1jcD_zw",
        "username": "17zzzzzzzz_",
        "post_date": "2026-4-11",
        "content": "誰有賣那種比較美式風格的衣服😭\n最近很缺那種一般基礎款的短袖\n但上面有文字 圖案等等的\n不要只有素踢的那種\n其他美式服裝也看看😚",
        "likes": 185,
        "comments": 54,
        "reposts": 4,
        "shares": 60,
        "keyword": "美式復古"
      },
      {
        "permalink": "https://www.threads.com/@ziunaye/post/DMky2lPTdrX",
        "username": "ziunaye",
        "post_date": "2025-7-26",
        "content": "帥吧 新風格",
        "likes": 18000,
        "comments": 73,
        "reposts": 285,
        "shares": 700,
        "keyword": "美式復古"
      },
      {
        "permalink": "https://www.threads.com/@ieeeei_ii_8/post/DXdc36Ykbtq",
        "username": "ieeeei_ii_8",
        "post_date": "2026-4-23",
        "content": "雙北哪裡有這種風格ㄉ衣服呀\n救救我(T_T)",
        "likes": 2207,
        "comments": 52,
        "reposts": 145,
        "shares": 411,
        "keyword": "美式復古"
      },
      {
        "permalink": "https://www.threads.com/@kacaw.kaokoy.cikatopay/post/DU9xKkSACWT",
        "username": "kacaw.kaokoy.cikatopay",
        "post_date": "2026-2-20",
        "content": "阿美族的穿衣敏感度\n#阿美族",
        "likes": 4725,
        "comments": 125,
        "reposts": 90,
        "shares": 149,
        "keyword": "阿美咔嘰"
      },
      {
        "permalink": "https://www.threads.com/@77.linnaa_/post/DSpneNPEq4c",
        "username": "77.linnaa_",
        "post_date": "2025-12-24",
        "content": "安美有PLAVE 卡包跟娃專了😳",
        "likes": 16,
        "comments": 0,
        "reposts": 0,
        "shares": 0,
        "keyword": "阿美咔嘰"
      },
      {
        "permalink": "https://www.threads.com/@girl98818vip/post/C-w5isHPBZw",
        "username": "girl98818vip",
        "post_date": "2024-8-17",
        "content": "久違的服裝😂\n花蓮 阿美❤️",
        "likes": 122,
        "comments": 0,
        "reposts": 0,
        "shares": 0,
        "keyword": "阿美咔嘰"
      },
      {
        "permalink": "https://www.threads.com/@milktea.milktea.351/post/DL9wVgRSUwN",
        "username": "milktea.milktea.351",
        "post_date": "2025-7-11",
        "content": "我阿美族\n你們呢",
        "likes": 1290,
        "comments": 26,
        "reposts": 6,
        "shares": 35,
        "keyword": "阿美咔嘰"
      }
    ]
  },
  "2026-05-02": {
    "keyword_tags": [
      "男生穿搭",
      "美式復古",
      "阿美咔嘰"
    ],
    "ai_summary": {
      "title": "今日 Threads 穿搭熱門趨勢追蹤：男性穿搭美學與復古風格復興",
      "intro": "今日 Threads 的穿搭討論高度集中於「男性時尚」的視覺呈現，尤其是強調色系搭配與日系中性風格。大數據顯示，具有高度實用性的穿搭模板以及集體式的帥氣穿搭展現獲得最高關注。此外，復古風格的討論已從美式復古延伸至 19 世紀西洋古典美學與芭蕾少女風（Balletcore）的混搭，顯示出使用者對於精緻美學與小眾服飾文化的強烈渴望。",
      "highlights": [
        {
          "title": "男性群體時尚的力量：帥氣穿搭的視覺饗宴",
          "description": "該貼文展示了一群熱愛打扮的男生出門的情境，引發了壓倒性的社群關注。這反映出 Threads 使用者對於高層次、精緻感的男性團體視覺呈現具有極高的互動率。",
          "url": "https://www.threads.com/@joseph_0102/post/DNfOCcYzYwG"
        },
        {
          "title": "實用主義至上：八套男生穿搭顏色模板",
          "description": "針對穿搭新手提供的實用色系建議，解決出門前的搭配煩惱。此類具備「收藏價值」與「懶人包」屬性的內容在穿搭圈內極受歡迎，互動數據表現優異。",
          "url": "https://www.threads.com/@mrdapper.co/post/DQ1u8NtAeXM"
        },
        {
          "title": "古典美學再崛起：19 世紀西洋服飾探討",
          "description": "網友分享對於 19 世紀初高腰剪裁（帝政裙）與復刻服飾的熱愛，反映出復古穿搭已不侷限於近現代，正朝向歷史精緻美學與細節考究的方向發展。",
          "url": "https://www.threads.com/@ladyl.2015/post/DXuOlYvE4IG"
        },
        {
          "title": "日系中性風持續走熱：男性裙裝與疊穿潮流",
          "description": "使用者積極尋求夏季日系中性穿搭建議，特別點出對「褲裙」與「多層次疊穿」的興趣，顯示男性穿搭市場正逐漸打破傳統性別框架，追求更多元化的剪裁設計。",
          "url": "https://www.threads.com/@we.0011___/post/DXq15Y9knf8"
        },
        {
          "title": "小眾風格融合：古著與芭蕾元素的結合",
          "description": "討論熱度涵蓋了古著、日系以及近期流行的芭蕾元素（Balletcore），顯示出台灣 Threads 用戶對於將不同風格（如波點、飾品疊穿）進行混搭的高度意願。",
          "url": "https://www.threads.com/@llama.467744/post/DU-xuoWEgg2"
        }
      ]
    },
    "posts": [
      {
        "permalink": "https://www.threads.com/@mrdapper.co/post/DQ1u8NtAeXM",
        "username": "mrdapper.co",
        "post_date": "2025-11-9",
        "content": "8套穿搭顏色模板送給大家！\n出門前跟著搭就OK～超實用🔥✨\n收藏起來不然找不到啦！！發給朋友一起分享！",
        "likes": 7346,
        "comments": 152,
        "reposts": 754,
        "shares": 8922,
        "keyword": "男生穿搭"
      },
      {
        "permalink": "https://www.threads.com/@hahahaluirr/post/DIrRnliz867",
        "username": "hahahaluirr",
        "post_date": "2025-4-20",
        "content": "男生會穿搭真的很香\n希望能蓋起一個男生穿搭樓(⌯︎¤̴̶̷̀ ᴗ ¤̴̶̷́⌯︎)✧",
        "likes": 13000,
        "comments": 1048,
        "reposts": 306,
        "shares": 2102,
        "keyword": "男生穿搭"
      },
      {
        "permalink": "https://www.threads.com/@ox.studio__/post/DSSpAC8Egji",
        "username": "ox.studio__",
        "post_date": "2025-12-15",
        "content": "一天發三套男生穿搭\n會有人看見我們嗎👀",
        "likes": 1177,
        "comments": 16,
        "reposts": 43,
        "shares": 270,
        "keyword": "男生穿搭"
      },
      {
        "permalink": "https://www.threads.com/@joseph_0102/post/DNfOCcYzYwG",
        "username": "joseph_0102",
        "post_date": "2025-8-18",
        "content": "跟一群愛打扮的男生出門是什麼樣的體驗",
        "likes": 67000,
        "comments": 1681,
        "reposts": 1933,
        "shares": 6140,
        "keyword": "男生穿搭"
      },
      {
        "permalink": "https://www.threads.com/@we.0011___/post/DXq15Y9knf8",
        "username": "we.0011___",
        "post_date": "3天",
        "content": "求求了\n想參考男生夏天的中性日系穿搭\n特別是褲裙的部分\n我衣櫃裡沒幾件能搭\n想順便更新整理一波 謝謝🙏",
        "likes": 844,
        "comments": 139,
        "reposts": 62,
        "shares": 249,
        "keyword": "男生穿搭"
      },
      {
        "permalink": "https://www.threads.com/@ladyl.2015/post/DXuOlYvE4IG",
        "username": "ladyl.2015",
        "post_date": "2天",
        "content": "最近看到有人在復刻清朝服飾走在路上\n蠻羨慕也佩服他對於喜好的堅持\n想問脆上有人也喜歡\n19世紀初西洋女性服飾 / 帝政裙 嗎？\n那種復古的高腰剪裁跟古典美真的好迷人，\n好想知道台灣有沒有人在玩這時期的復刻或穿搭？",
        "likes": 4892,
        "comments": 195,
        "reposts": 177,
        "shares": 160,
        "keyword": "美式復古"
      },
      {
        "permalink": "https://www.threads.com/@deepbreath.9/post/DXvtH6CEdtT",
        "username": "deepbreath.9",
        "post_date": "1天",
        "content": "筆記一下\n北美館超現實主義展的各種符號",
        "likes": 417,
        "comments": 26,
        "reposts": 34,
        "shares": 43,
        "keyword": "美式復古"
      },
      {
        "permalink": "https://www.threads.com/@lov.ekissu/post/DXZO9QOGTHU",
        "username": "lov.ekissu",
        "post_date": "2026-4-21",
        "content": "我感觉明星要是很土的话，那说明这辈子他就没有时尚细胞....天天和时尚圈，时尚杂志打交道，没事还会被邀请去看秀，那么多铺天盖地的审美积累都提高不了他的审美，那我就感觉他这个人骨子里就土",
        "likes": 1554,
        "comments": 35,
        "reposts": 21,
        "shares": 62,
        "keyword": "美式復古"
      },
      {
        "permalink": "https://www.threads.com/@moqifox/post/DXZgRWUksZC",
        "username": "moqifox",
        "post_date": "2026-4-21",
        "content": "有时尚感的都是有一些酷儿气质的，顺直基本和时尚无缘了",
        "likes": 1434,
        "comments": 9,
        "reposts": 51,
        "shares": 74,
        "keyword": "美式復古"
      },
      {
        "permalink": "https://www.threads.com/@llama.467744/post/DU-xuoWEgg2",
        "username": "llama.467744",
        "post_date": "2026-2-20",
        "content": "想收日系、古著、有波點/芭蕾元素的漂亮衣服\n或中裙、各種疊穿好物><首飾小東西等等也可以看看！",
        "likes": 79,
        "comments": 82,
        "reposts": 3,
        "shares": 0,
        "keyword": "美式復古"
      },
      {
        "permalink": "https://www.threads.com/@editn_17/post/DVv995oEwh1",
        "username": "editn_17",
        "post_date": "2026-3-11",
        "content": "我自行宣布\n第♾️屆 《原住民美女帥哥》\n正式開始\n選手如下：",
        "likes": 7607,
        "comments": 2717,
        "reposts": 194,
        "shares": 1597,
        "keyword": "阿美咔嘰"
      },
      {
        "permalink": "https://www.threads.com/@el_maaha1official/post/DWqZGQzkSii",
        "username": "el_maaha1official",
        "post_date": "2026-4-3",
        "content": "阿美族",
        "likes": 12000,
        "comments": 541,
        "reposts": 130,
        "shares": 4082,
        "keyword": "阿美咔嘰"
      },
      {
        "permalink": "https://www.threads.com/@nyg810824/post/DFnYA-my2DE",
        "username": "nyg810824",
        "post_date": "2025-2-3",
        "content": "弘爺、拉亞、麥味登、阿寶、美而美\n誰的什麼品項最頂？",
        "likes": 1014,
        "comments": 226,
        "reposts": 52,
        "shares": 234,
        "keyword": "阿美咔嘰"
      },
      {
        "permalink": "https://www.threads.com/@kelly__0227/post/DOiRM4Tkomn",
        "username": "kelly__0227",
        "post_date": "2025-9-13",
        "content": "米干都只吃阿美⋯還有推薦的嗎🤣\n我知道的只有那幾家大間的哈哈哈",
        "likes": 1190,
        "comments": 117,
        "reposts": 60,
        "shares": 527,
        "keyword": "阿美咔嘰"
      },
      {
        "permalink": "https://www.threads.com/@adorableabu/post/DXJu_5ICXPZ",
        "username": "adorableabu",
        "post_date": "2026-4-15",
        "content": "阿努：吵什麼\nKESHA、維心、惟惟醬：😱😱😱\n來源：悍將應援花絮 twitch",
        "likes": 965,
        "comments": 14,
        "reposts": 10,
        "shares": 63,
        "keyword": "阿美咔嘰"
      }
    ]
  },
  "2026-05-01": {
    "keyword_tags": [
      "男生穿搭",
      "美式復古",
      "阿美咔嘰"
    ],
    "ai_summary": {
      "title": "今日 Threads 穿搭趨勢與美式復古風潮觀察",
      "intro": "今日 Threads 上的時尚討論聚焦於兩大核心：首先是『男裝穿搭的多樣性』，包含韓系風格靈感與男女審美差異的探討；其次是『美式復古風格』的高度關注，尤其是融合畢業季或校園主題的雜誌感視覺。男裝部分以實用工具型與韓式部落客分享最受歡迎，而復古風格則呈現出美式學院風與懷舊視覺美學的強烈需求。",
      "highlights": [
        {
          "title": "美式復古雜誌風：校園穿搭的新巔峰",
          "description": "用戶 dawnsky_ouo 分享了極具視覺衝擊的美式復古雜誌感穿搭，將畢業紀念冊封面與懷舊時尚結合，獲得超過 8,000 個讚，顯示復古影像美學在校園族群中具有極大影響力。",
          "url": "https://www.threads.com/@dawnsky_ouo/post/DWBJhWykasJ"
        },
        {
          "title": "韓系男裝靈感：穿搭部落客資源整合",
          "description": "針對想進修穿搭的男性使用者，taichiu727 整理了 2024 年必追的韓系男生穿搭部落格清單，提供具體的風格學習路徑，反映出韓系簡約風格在 Threads 上的主流地位。",
          "url": "https://www.threads.com/@taichiu727/post/DAnQCJ5vJoD"
        },
        {
          "title": "男女審美大對決：穿搭偏好的視角衝突",
          "description": "elf_121vivi 探討了『男生喜歡的穿搭』與『女生喜歡的男生穿搭』之間的差異，引發大量互動討論，顯示社群對於『好感度穿搭』與『自我表達』之間的權衡有高度興趣。",
          "url": "https://www.threads.com/@elf_121vivi/post/DBJOuwlyXi5"
        },
        {
          "title": "美式復古學院風 (Ivy Style) 的穿搭諮詢",
          "description": "雖然互動數較低，但 caspi.an999 的求救貼文展現了市場對於特定復古細分風格（如美式學院風）的購買需求與實穿困難點，特別是針對特定體型（如腿粗）的穿搭建議需求。",
          "url": "https://www.threads.com/@caspi.an999/post/DVL5nYLAWoE"
        }
      ]
    },
    "posts": [
      {
        "permalink": "https://www.threads.com/@c.iceyyy/post/DBOk8DcyXrq",
        "username": "c.iceyyy",
        "post_date": "2024-10-17",
        "content": "小男生穿搭☕️🙂‍↔️",
        "likes": 3456,
        "comments": 128,
        "reposts": 3,
        "shares": 98,
        "keyword": "男生穿搭"
      },
      {
        "permalink": "https://www.threads.com/@taichiu727/post/DAnQCJ5vJoD",
        "username": "taichiu727",
        "post_date": "2024-10-2",
        "content": "2024學習韓系必追的男生穿搭部落格\n真的都蠻會穿搭的\n給了我很多的靈感",
        "likes": 3472,
        "comments": 71,
        "reposts": 363,
        "shares": 1566,
        "keyword": "男生穿搭"
      },
      {
        "permalink": "https://www.threads.com/@elf_121vivi/post/DBJOuwlyXi5",
        "username": "elf_121vivi",
        "post_date": "2024-10-15",
        "content": "關於穿搭\n男生喜歡的 vs 女生喜歡的",
        "likes": 2519,
        "comments": 102,
        "reposts": 9,
        "shares": 145,
        "keyword": "男生穿搭"
      },
      {
        "permalink": "https://www.threads.com/@emotional_tw/post/C-WvyuChW3K",
        "username": "emotional_tw",
        "post_date": "2024-8-7",
        "content": "男生穿搭看這邊！！\n關注我們讓你學習這種穿搭👏",
        "likes": 1229,
        "comments": 16,
        "reposts": 28,
        "shares": 94,
        "keyword": "男生穿搭"
      },
      {
        "permalink": "https://www.threads.com/@dawnsky_ouo/post/DWBJhWykasJ",
        "username": "dawnsky_ouo",
        "post_date": "2026-3-18",
        "content": "真的好希望可以被選上畢冊封面\n很努力的在符合這次的主題了（美式復古雜誌風）✋😭🤚\n偷偷拉一下同校的票\n祝高三生的大家不管是學測個申還是分科等等都順利，上自己理想的學校！",
        "likes": 8285,
        "comments": 92,
        "reposts": 164,
        "shares": 228,
        "keyword": "美式復古"
      },
      {
        "permalink": "https://www.threads.com/@nico6363728181/post/DXCBhHMFHpU",
        "username": "nico6363728181",
        "post_date": "2026-4-12",
        "content": "台灣女生想找美式復古 風格衣服 請收藏🤩🤩",
        "likes": 20,
        "comments": 2,
        "reposts": 2,
        "shares": 10,
        "keyword": "美式復古"
      },
      {
        "permalink": "https://www.threads.com/@learnenglishwithryan/post/DEeHT3Jy1yG",
        "username": "learnenglishwithryan",
        "post_date": "2025-1-6",
        "content": "提升英語必看6部學英文神劇\n1️⃣ 《怪奇物語》Stranger Things：80年代復古對話+青少年日常英文\n2️⃣ 《權力的遊戲》Game of Thrones：提升高級詞彙，學貴族式英文！\n3️⃣ 《黃石公園》Yellowstone：美式鄉村英文，帶你了解地道美國文化\n4️⃣ 《繼承之戰》Succession：職場+家族鬥爭，精準商務英文必學\n5️⃣ 《紙牌屋》House of Cards：政治與權謀對話，拓展正式語言能力\n6️⃣ 《六人行》Friends：經典情景對話，最輕鬆的美式口語教材！\n以上有沒有你看過的劇？\n英語學習",
        "likes": 830,
        "comments": 13,
        "reposts": 59,
        "shares": 120,
        "keyword": "美式復古"
      },
      {
        "permalink": "https://www.threads.com/@caspi.an999/post/DVL5nYLAWoE",
        "username": "caspi.an999",
        "post_date": "2026-2-25",
        "content": "廣大的脆友們\n本人過幾天要參加個活動\n穿著的主題是［復古美式學院風］\n想請問各位有建議怎麼穿搭或去哪裡買的地方嗎？\n本人腿偏粗要穿長褲\n麻煩各位脆友們幫忙",
        "likes": 4,
        "comments": 14,
        "reposts": 0,
        "shares": 0,
        "keyword": "美式復古"
      },
      {
        "permalink": "https://www.threads.com/@33.write/post/DHvypqwzYYP",
        "username": "33.write",
        "post_date": "2025-3-28",
        "content": "\\國父紀念館附近美食第二彈✨/\n上次發文獲得好多回饋，也有看留言去吃了幾家脆友推薦的店家，於是就生出part 2，希望有幫助到大家🤤\n📍PLACEEE場所\n延吉街旁的深夜咖啡廳，咖啡餐點甜點都很有水準，咖啡很有特色，端上來還以為點了調酒！松露野菇義大利麵的菇味超重超愛…\n📍潮肉壽喜燒\n富有創意的壽喜燒吃到飽，中間店員會來桌旁兩次製作特色餐點（泰式酸辣豬、起司牛肉捲），自助吧也很多樣化！\n📍PPM 餐酒館\n有點美式復古的裝潢，特愛抹茶巴斯克&優格炸雞！評論有提到像服務態度不好、不會主動倒水..等等問題，但我自己去了兩次都沒遇到～\n📍陳記麻辣食堂\n我心目中的台北螺螄粉No.1！湯頭很濃郁有層次（有點那種大骨湯的感覺），配料辣度都可以調整，但他小辣是一般的中辣（我平常大概吃小辣，我去都點微辣～）\n📍嵩 sung\n沒有訂位很難吃到的人氣餐酒館，餐前介紹感到滿滿的專業度，生日會幫忙拍照&送提拉米蘇，很適合聚會，橘色大牆很有辨識度\n📍宜品福州乾拌麵\n平價美味的平民小吃，拌麵湯品都很不錯！\n（環境也是比一般小吃店乾淨）\n(留言續）",
        "likes": 174,
        "comments": 2,
        "reposts": 22,
        "shares": 126,
        "keyword": "美式復古"
      },
      {
        "permalink": "https://www.threads.com/@francis__1450/post/DHQyDpLSogP",
        "username": "linlin2322",
        "post_date": "2025-3-17",
        "content": "最勇敢、漂亮的掌旗官，阿美美女!\nfrancis__1450",
        "likes": 2871,
        "comments": 11,
        "reposts": 18,
        "shares": 2,
        "keyword": "阿美咔嘰"
      },
      {
        "permalink": "https://www.threads.com/@168__fen/post/C6n-x5-yk38",
        "username": "168__fen",
        "post_date": "2024-5-6",
        "content": "我很驕傲我是阿美族☺️",
        "likes": 752,
        "comments": 18,
        "reposts": 0,
        "shares": 0,
        "keyword": "阿美咔嘰"
      }
    ]
  }
}