{
  "2026-07-01": {
    "keyword_tags": [
      "男生穿搭",
      "美式復古",
      "阿美咔嘰"
    ],
    "ai_summary": {
      "title": "今日 Threads 穿搭熱門趨勢：質感男裝與美式復古熱議",
      "intro": "今日 Threads 穿搭社群討論主要聚焦於「質感男裝升級」與「美式復古風格」兩大面向。男性使用者表現出對廉價快時尚的疲乏，開始轉向尋求具備日韓簡約感的質感店家；而復古風格方面，美式亞裔 (ABG) 風格的審美帶動力，以及對經典美式 Polo 衫等單品的搜尋熱度，顯示出復古與地域性風格轉化的強烈需求。",
      "highlights": [
        {
          "title": "質感男裝寶藏店清單推薦",
          "description": "網民熱烈收藏針對避開淘寶雷店的男裝店鋪推薦，涵蓋日系與韓系簡約風，強調衣服質感與穿搭氛圍的整體升級。",
          "url": "https://www.threads.com/@chichiyuyu77/post/DZ60t0VkRbi"
        },
        {
          "title": "美式亞裔審美風格的影響力",
          "description": "觀察到前往美國後的亞裔女性在風格上趨向經典美式妝造，引發社群對於特定地理審美流行風向帶動效應的討論。",
          "url": "https://www.threads.com/@auxirowenra/post/DSlUtOAjYZ-"
        },
        {
          "title": "經典單品搜尋：美式復古 Polo 衫",
          "description": "使用者主動尋求美式復古 Polo 衫的購入渠道，顯示經典美式單品在復古運動風潮下仍具有穩固的市場需求。",
          "url": "https://www.threads.com/@_122yoo/post/DZ49FX4j0dS"
        },
        {
          "title": "情侶混穿現象與中性穿搭趣味",
          "description": "關於男生穿另一半衣服的趣味討論，獲得大量互動，反映出社群對於模糊性別界限、共享衣櫥等生活化穿搭話題的高度共鳴。",
          "url": "https://www.threads.com/@lt._.09/post/DZLOIjOk-GL"
        }
      ]
    },
    "posts": [
      {
        "permalink": "https://www.threads.com/@chichiyuyu77/post/DZ60t0VkRbi",
        "username": "chichiyuyu77",
        "post_date": "2026-6-23",
        "content": "拜託所有男生！！衣服不想再亂買淘寶貨的\n這篇直接收藏起來🥹\n整理幾間質感很好的男裝寶藏店\n不是那種照片很帥、收到像抹布的雷店\n有韓系氛圍感也有日系簡約風\n隨便搭牛仔褲、西裝褲都很好看\n想把穿搭升級的男生真的先存！！",
        "likes": 9,
        "comments": 4,
        "reposts": 14,
        "shares": 0,
        "keyword": "男生穿搭"
      },
      {
        "permalink": "https://www.threads.com/@lt._.09/post/DZLOIjOk-GL",
        "username": "lt._.09",
        "post_date": "2026-6-4",
        "content": "男生是不是都很喜歡穿另一半的衣服",
        "likes": 190,
        "comments": 35,
        "reposts": 3,
        "shares": 136,
        "keyword": "男生穿搭"
      },
      {
        "permalink": "https://www.threads.com/@9sun___/post/DZWa7TCmaMj",
        "username": "9sun___",
        "post_date": "2026-6-9",
        "content": "目前討論度依舊火熱的 5 種室內設計風格：\n1.日式北歐風：簡單來說，就是「北歐風的機能 ＋ 日式無印的溫潤」\n2.奶油法式風：拍照狂熱者的最愛，仙氣飄飄、自帶濾鏡\n3.侘寂風：紅了兩年依然在神壇上的人人都愛風\n4.胡桃木復古風：近期的大熱門！搭配高飽磁磚，打造英倫復古感\n5輕工業風格：不鏽鋼層架 ＋ 毛毛蟲沙發，一定還會有一盞野口勇或北歐金屬蘑菇燈來搭配\n你家也是這幾種風格嗎？放上你家的照片一起來欣賞吧！",
        "likes": 22,
        "comments": 7,
        "reposts": 1,
        "shares": 6,
        "keyword": "美式復古"
      },
      {
        "permalink": "https://www.threads.com/@auxirowenra/post/DSlUtOAjYZ-",
        "username": "auxirowenra",
        "post_date": "2025-12-22",
        "content": "感觉身边去了美国的很多女生朋友无论之前风格如何都清一色变成了经典美式亚裔妆容。。。震惊之余对美国审美流行风向的带动效果有一丝丝恐惧。。。",
        "likes": 347,
        "comments": 43,
        "reposts": 2,
        "shares": 5,
        "keyword": "美式復古"
      },
      {
        "permalink": "https://www.threads.com/@vento_ceilingfan/post/DZHjnavEoJc",
        "username": "vento_ceilingfan",
        "post_date": "2026-6-3",
        "content": "你喜歡溫潤原木、藤編的東南亞自然風格，\n還是\n典雅且簡約的美式風格呢?\n或是其他? 跟我們聊聊👋",
        "likes": 3,
        "comments": 0,
        "reposts": 0,
        "shares": 0,
        "keyword": "美式復古"
      },
      {
        "permalink": "https://www.threads.com/@_122yoo/post/DZ49FX4j0dS",
        "username": "_122yoo",
        "post_date": "2026-6-22",
        "content": "美式復古Polo衫哪裡可以買",
        "likes": 4,
        "comments": 7,
        "reposts": 0,
        "shares": 0,
        "keyword": "美式復古"
      },
      {
        "permalink": "https://www.threads.com/@zhen0421_/post/DaE4-H-miRj",
        "username": "zhen0421_",
        "post_date": "4天",
        "content": "想找北高室內設計裝潢\n風格想要日系簡約～",
        "likes": 59,
        "comments": 68,
        "reposts": 1,
        "shares": 5,
        "keyword": "美式復古"
      },
      {
        "permalink": "https://www.threads.com/@xykin__/post/DW9QqD6D8jd",
        "username": "xykin__",
        "post_date": "2026-4-10",
        "content": "想認識很多阿米跟萬斯ㅠㅠ\n歡迎直戳！",
        "likes": 183,
        "comments": 55,
        "reposts": 1,
        "shares": 8,
        "keyword": "阿美咔嘰"
      },
      {
        "permalink": "https://www.threads.com/@fenshengest/post/DZd96eHgNSe",
        "username": "fenshengest",
        "post_date": "2026-6-12",
        "content": "阿密特要来了\n@amit_feat_amei",
        "likes": 112,
        "comments": 2,
        "reposts": 3,
        "shares": 0,
        "keyword": "阿美咔嘰"
      },
      {
        "permalink": "https://www.threads.com/@hank_madaw.1994/post/DaHn95EGv3O",
        "username": "hank_madaw.1994",
        "post_date": "2天",
        "content": "有餒 這個動作應該只有阿美族看得懂💯",
        "likes": 23000,
        "comments": 100,
        "reposts": 299,
        "shares": 461,
        "keyword": "阿美咔嘰"
      },
      {
        "permalink": "https://www.threads.com/@littletravelone/post/DRHmqeegaq-",
        "username": "littletravelone",
        "post_date": "2025-11-16",
        "content": "安美竟然有櫻蘭抽卡機台✨\n這是什麼文藝復興",
        "likes": 4492,
        "comments": 81,
        "reposts": 344,
        "shares": 1666,
        "keyword": "阿美咔嘰"
      },
      {
        "permalink": "https://www.threads.com/@trustmylife0730/post/DZ_Qtcaky-7",
        "username": "trustmylife0730",
        "post_date": "6天",
        "content": "不管是支持脫北或是支持阿美的人，拜託冷靜…各自都有支持者，看不慣真的就封鎖各自安好就好，兩邊吵成這樣是可以吵出什麼結果嗎？！\n吵贏是有什麼獎勵？ 只會讓那些藍白草看笑話甚至見縫插針跟著起鬨亂搞，拜託能不能消停一下？ 🙄🙄🙄",
        "likes": 58,
        "comments": 43,
        "reposts": 4,
        "shares": 12,
        "keyword": "阿美咔嘰"
      }
    ]
  },
  "2026-06-30": {
    "keyword_tags": [
      "男生穿搭",
      "美式復古",
      "阿美咔嘰"
    ],
    "ai_summary": {
      "title": "今日 Threads 穿搭趨勢與美式復古風格觀察",
      "intro": "今日 Threads 的穿搭討論呈現兩極化發展：一方面，社群對「男女打扮差異」展現高度共鳴，引發男性使用者對於提升穿搭技巧的迫切需求；另一方面，「美式復古」與「辣妹風」持續延燒，使用者不僅尋求特定風格（如 Cortis 風格）的店家，更積極分享 vintage 與設計感強烈的網拍資源。值得注意的是，「阿美咔嘰」標籤在本次採集數據中出現關鍵字誤導，多數高熱度貼文實為原住民族群文化互動，而非純粹的服飾風格討論。",
      "highlights": [
        {
          "title": "男女打扮精緻度差異引發熱議",
          "description": "一則關於「女生盛裝打扮與男生隨性穿著」的幽默貼文獲得近五千讚，反映出大眾對於目前社交場合中性別打扮落差的觀察與高度共鳴。",
          "url": "https://www.threads.com/@samuel198799/post/DZ3rozECZid"
        },
        {
          "title": "美式復古辣妹風格店家推薦",
          "description": "網友精確鎖定「Cortis 風格」與「美式復古」進行寶藏店鋪分享，獲得極高關注，顯示社群對於特定次文化美學與實際購買管道的強烈渴望。",
          "url": "https://www.threads.com/@kittenmeowbaby/post/DZmYTFaga-E"
        },
        {
          "title": "男裝穿搭教學需求攀升",
          "description": "Threads 上湧現男性使用者公開尋求穿搭參考與建議，顯示男性穿搭市場在社群中存在顯著的內容缺口與學習需求。",
          "url": "https://www.threads.com/@0120.roy/post/DY-CQ25k2we"
        },
        {
          "title": "復古與特色設計風格資源徵求",
          "description": "使用者積極尋求美式、辣妹、Vintage 及具有設計特色的網拍推薦，體現出 Threads 作為潮流資訊交換中心的機能。",
          "url": "https://www.threads.com/@saorsagis/post/DRv0HMCj_8q"
        }
      ]
    },
    "posts": [
      {
        "permalink": "https://www.threads.com/@samuel198799/post/DZ3rozECZid",
        "username": "samuel198799",
        "post_date": "2026-6-22",
        "content": "女生盛裝打扮 男生有穿衣服",
        "likes": 4931,
        "comments": 159,
        "reposts": 35,
        "shares": 449,
        "keyword": "男生穿搭"
      },
      {
        "permalink": "https://www.threads.com/@0120.roy/post/DY-CQ25k2we",
        "username": "0120.roy",
        "post_date": "2026-5-30",
        "content": "各位男生把自己的穿搭傳上來我參考參考\n真的不會穿搭",
        "likes": 1742,
        "comments": 441,
        "reposts": 61,
        "shares": 405,
        "keyword": "男生穿搭"
      },
      {
        "permalink": "https://www.threads.com/@saorsagis/post/DRv0HMCj_8q",
        "username": "saorsagis",
        "post_date": "2025-12-2",
        "content": "有沒有這種風格的網拍或淘寶店\n美式、辣妹、vintage、古早、設計有特色等等 請推薦給我謝謝！",
        "likes": 483,
        "comments": 18,
        "reposts": 18,
        "shares": 86,
        "keyword": "美式復古"
      },
      {
        "permalink": "https://www.threads.com/@mikika_232/post/DZ7bqNKE69j",
        "username": "mikika_232",
        "post_date": "6天",
        "content": "穿搭 造型 风格 我好陌生",
        "likes": 495,
        "comments": 20,
        "reposts": 3,
        "shares": 65,
        "keyword": "美式復古"
      },
      {
        "permalink": "https://www.threads.com/@cry.laugh/post/DWJQ2ksAWH0",
        "username": "cry.laugh",
        "post_date": "2026-3-21",
        "content": "麻煩脆上大神給點建議\n我想軟裝改成北歐現代的感覺 🥹",
        "likes": 140,
        "comments": 74,
        "reposts": 1,
        "shares": 44,
        "keyword": "美式復古"
      },
      {
        "permalink": "https://www.threads.com/@kittenmeowbaby/post/DZmYTFaga-E",
        "username": "kittenmeowbaby",
        "post_date": "2026-6-15",
        "content": "女生想要穿得像Cortis的，一定要看這家寶藏店！！美式復古風超好看❤️‍🔥",
        "likes": 4407,
        "comments": 55,
        "reposts": 615,
        "shares": 2059,
        "keyword": "美式復古"
      },
      {
        "permalink": "https://www.threads.com/@august.a.g/post/DZfU8CzlKM1",
        "username": "august.a.g",
        "post_date": "2026-6-12",
        "content": "*,.*♫____1920年代復古風 • GPT____♪.*\n你那裡的風也有花香嗎?\n⇆ ㅤㅤㅤ◁ ㅤㅤ❚❚ ㅤㅤ▷ ㅤㅤㅤ↻",
        "likes": 37,
        "comments": 17,
        "reposts": 2,
        "shares": 4,
        "keyword": "美式復古"
      },
      {
        "permalink": "https://www.threads.com/@ren16nie/post/DY3amjsgUbW",
        "username": "ren16nie",
        "post_date": "2026-5-28",
        "content": "想蓋個原住民顏值樓\n男女都可以 不知道蓋不蓋得起來",
        "likes": 6825,
        "comments": 1348,
        "reposts": 91,
        "shares": 622,
        "keyword": "阿美咔嘰"
      },
      {
        "permalink": "https://www.threads.com/@amis_0120/post/DaF5Y09E_7s",
        "username": "amis_0120",
        "post_date": "2天",
        "content": "純阿美 參戰🤣",
        "likes": 2576,
        "comments": 45,
        "reposts": 5,
        "shares": 34,
        "keyword": "阿美咔嘰"
      },
      {
        "permalink": "https://www.threads.com/@bts7armybestie/post/DZh45EjmUPU",
        "username": "bts7armybestie",
        "post_date": "2026-6-13",
        "content": "超猛阿米！偶像！\n抓牛阿米一生推\nchangsinny\n2026-6-13\n大型抓牛現場\n剛剛在體育場外看到正在面交的黃牛，機智如我先偷拍再說😆 然後就去找黑衣警衛，說出關鍵字\"selling ticket\"，黑衣警衛立刻衝出去。\n黃牛死不承認，殊不知我有影片，爽!!\n死黃牛我沒票你也別想發財!!!\nRP剛剛儲值10,000點✌️",
        "likes": 9289,
        "comments": 311,
        "reposts": 200,
        "shares": 1056,
        "keyword": "阿美咔嘰"
      },
      {
        "permalink": "https://www.threads.com/@changsinny/post/DZhcvQdE2DZ",
        "username": "changsinny",
        "post_date": "2026-6-13",
        "content": "大型抓牛現場\n剛剛在體育場外看到正在面交的黃牛，機智如我先偷拍再說😆 然後就去找黑衣警衛，說出關鍵字\"selling ticket\"，黑衣警衛立刻衝出去。\n黃牛死不承認，殊不知我有影片，爽!!\n死黃牛我沒票你也別想發財!!!\nRP剛剛儲值10,000點✌️",
        "likes": 9289,
        "comments": 311,
        "reposts": 200,
        "shares": 1056,
        "keyword": "阿美咔嘰"
      },
      {
        "permalink": "https://www.threads.com/@chenlin3914/post/DM4NANjxJp2",
        "username": "chenlin3914",
        "post_date": "2025-8-3",
        "content": "這個妹妹真的漂亮\n阿美族的改應❤️",
        "likes": 8688,
        "comments": 120,
        "reposts": 27,
        "shares": 465,
        "keyword": "阿美咔嘰"
      }
    ]
  },
  "2026-06-29": {
    "keyword_tags": [
      "男生穿搭",
      "美式復古",
      "阿美咔嘰"
    ],
    "ai_summary": {
      "title": "今日 Threads 穿搭熱門追蹤 (AI 摘要未啟用)",
      "intro": "今日共擷取到 14 篇相關貼文。以下是部分精選內容：",
      "highlights": [
        {
          "title": "來自 @hahahaluirr 的貼文",
          "description": "男生會穿搭真的很香 希望能蓋起一個男生穿搭樓(⌯︎¤̴̶̷̀ ᴗ ¤̴̶̷́⌯︎)✧...",
          "url": "https://www.threads.com/@hahahaluirr/post/DIrRnliz867"
        },
        {
          "title": "來自 @cds2496 的貼文",
          "description": "想看三十歲的男生都怎麼穿搭...",
          "url": "https://www.threads.com/@cds2496/post/DZ7QwkMEigr"
        },
        {
          "title": "來自 @x.c.1.1.4 的貼文",
          "description": "潮潮們 有人可以說一下這種大熱天你們是怎麼穿搭的嗎 我能想到的好看穿搭都是冬天的樣子🥲...",
          "url": "https://www.threads.com/@x.c.1.1.4/post/DZGDo_dEl90"
        },
        {
          "title": "來自 @ml02_10 的貼文",
          "description": "不知道該怎麼選男生夏季夏季穿搭 哥們請求支援😆😆...",
          "url": "https://www.threads.com/@ml02_10/post/DaDc6NTk_W4"
        },
        {
          "title": "來自 @amosliuliu 的貼文",
          "description": "為何台灣的裝潢不管怎麼看，跟美式的裝潢風格就差很多，即使像是張馨這種大師，裝潢很好看，但就不是道地的...",
          "url": "https://www.threads.com/@amosliuliu/post/DaB1ocsmdqW"
        }
      ]
    },
    "posts": [
      {
        "permalink": "https://www.threads.com/@hahahaluirr/post/DIrRnliz867",
        "username": "hahahaluirr",
        "post_date": "2025-4-20",
        "content": "男生會穿搭真的很香\n希望能蓋起一個男生穿搭樓(⌯︎¤̴̶̷̀ ᴗ ¤̴̶̷́⌯︎)✧",
        "likes": 13000,
        "comments": 1056,
        "reposts": 314,
        "shares": 2126,
        "keyword": "男生穿搭"
      },
      {
        "permalink": "https://www.threads.com/@cds2496/post/DZ7QwkMEigr",
        "username": "cds2496",
        "post_date": "5天",
        "content": "想看三十歲的男生都怎麼穿搭",
        "likes": 31,
        "comments": 37,
        "reposts": 6,
        "shares": 0,
        "keyword": "男生穿搭"
      },
      {
        "permalink": "https://www.threads.com/@x.c.1.1.4/post/DZGDo_dEl90",
        "username": "x.c.1.1.4",
        "post_date": "2026-6-2",
        "content": "潮潮們\n有人可以說一下這種大熱天你們是怎麼穿搭的嗎\n我能想到的好看穿搭都是冬天的樣子🥲",
        "likes": 304,
        "comments": 82,
        "reposts": 1,
        "shares": 8,
        "keyword": "男生穿搭"
      },
      {
        "permalink": "https://www.threads.com/@ml02_10/post/DaDc6NTk_W4",
        "username": "ml02_10",
        "post_date": "2天",
        "content": "不知道該怎麼選男生夏季夏季穿搭\n哥們請求支援😆😆",
        "likes": 86,
        "comments": 19,
        "reposts": 3,
        "shares": 34,
        "keyword": "男生穿搭"
      },
      {
        "permalink": "https://www.threads.com/@amosliuliu/post/DaB1ocsmdqW",
        "username": "amosliuliu",
        "post_date": "3天",
        "content": "為何台灣的裝潢不管怎麼看，跟美式的裝潢風格就差很多，即使像是張馨這種大師，裝潢很好看，但就不是道地的美式風格，想問大家主要原因是什麼？",
        "likes": 113,
        "comments": 77,
        "reposts": 45,
        "shares": 0,
        "keyword": "美式復古"
      },
      {
        "permalink": "https://www.threads.com/@nni.o3/post/DH7w5gRRzd0",
        "username": "nni.o3",
        "post_date": "2025-4-2",
        "content": "想嘗試美式或Y2K風格\n有爬文了但怕踩雷\n不知道美女們有沒有推薦的店😭🙏\n不懂就問脆",
        "likes": 1666,
        "comments": 43,
        "reposts": 74,
        "shares": 312,
        "keyword": "美式復古"
      },
      {
        "permalink": "https://www.threads.com/@shuhua7127/post/DZt_zRykd8O",
        "username": "shuhua7127",
        "post_date": "2026-6-18",
        "content": "美式復古早午餐咖啡店☕️✨\n老屋整理改造，粉綠復古風格＋霓虹燈氛圍，設備齊全可直接營業！\nBubble Gum · NewJeans",
        "likes": 50,
        "comments": 2,
        "reposts": 8,
        "shares": 0,
        "keyword": "美式復古"
      },
      {
        "permalink": "https://www.threads.com/@llama.467744/post/DU-xuoWEgg2",
        "username": "llama.467744",
        "post_date": "2026-2-20",
        "content": "想收日系、古著、有波點/芭蕾元素的漂亮衣服\n或中裙、各種疊穿好物><首飾小東西等等也可以看看！",
        "likes": 81,
        "comments": 81,
        "reposts": 3,
        "shares": 0,
        "keyword": "美式復古"
      },
      {
        "permalink": "https://www.threads.com/@josee165165/post/DZKeI3kkv9W",
        "username": "josee165165",
        "post_date": "2026-6-4",
        "content": "中年大叔🥸穿搭真的不能少帥氣的風格😂",
        "likes": 23,
        "comments": 1,
        "reposts": 0,
        "shares": 0,
        "keyword": "美式復古"
      },
      {
        "permalink": "https://www.threads.com/@y_u.9953/post/DZTs90gkznk",
        "username": "y_u.9953",
        "post_date": "2026-6-8",
        "content": "阿米棒也上岸了😭😭",
        "likes": 17,
        "comments": 5,
        "reposts": 0,
        "shares": 0,
        "keyword": "阿美咔嘰"
      },
      {
        "permalink": "https://www.threads.com/@ping.__14/post/DV0RJtbk9Bs",
        "username": "ping.__14",
        "post_date": "2026-3-13",
        "content": "想蓋個樓\n《最特別的婚紗照》\n我先來 我姐的😻",
        "likes": 29000,
        "comments": 1471,
        "reposts": 280,
        "shares": 3112,
        "keyword": "阿美咔嘰"
      },
      {
        "permalink": "https://www.threads.com/@able_0416/post/DV03FJBgQjM",
        "username": "able_0416",
        "post_date": "2026-3-13",
        "content": "阿美族🌾",
        "likes": 15000,
        "comments": 157,
        "reposts": 45,
        "shares": 121,
        "keyword": "阿美咔嘰"
      },
      {
        "permalink": "https://www.threads.com/@minuet_waiting/post/DZd1mfbj93L",
        "username": "minuet_waiting",
        "post_date": "2026-6-12",
        "content": "阿我的女聲優專區呢",
        "likes": 277,
        "comments": 22,
        "reposts": 1,
        "shares": 80,
        "keyword": "阿美咔嘰"
      },
      {
        "permalink": "https://www.threads.com/@ake._cwmm/post/DL0S5_LhOWV",
        "username": "ake._cwmm",
        "post_date": "2025-7-7",
        "content": "阿咪可能有喜歡被鞭打的怪癖",
        "likes": 28000,
        "comments": 208,
        "reposts": 1331,
        "shares": 8777,
        "keyword": "阿美咔嘰"
      }
    ]
  },
  "2026-06-28": {
    "keyword_tags": [
      "男生穿搭",
      "美式復古",
      "阿美咔嘰"
    ],
    "ai_summary": {
      "title": "今日 Threads 穿搭與復古趨勢分析報告",
      "intro": "今日 Threads 穿搭社群展現出強烈的風格分歧與實用導向。男裝領域主要圍繞在『韓系大眾風』與『日系昭和復古』的轉型討論；與此同時，『美式復古』已從單純的服裝風格延伸至生活風格、餐飲空間與相片修圖濾鏡。值得注意的是，機能防曬外套在炎夏中成為熱議單品，將美式與機能美學完美融合，並持續推升日本選物店與品牌（如 DAIWA PIER39, nanamica）的關注度。",
      "highlights": [
        {
          "title": "從台男秒變日系潮男：昭和復古穿搭指南",
          "description": "提供實用的昭和風格穿搭範本，幫助讀者快速掌握日系潮男精髓，獲得極高社群迴響。",
          "url": "https://www.threads.com/@lxz20002000/post/DVIPpIWkyP7"
        },
        {
          "title": "大阪日牌選物店深度導航：從城市機能到美式復古",
          "description": "詳細盤點大阪地區匯集 AURALEE、DAIWA PIER39 等高端日牌的選物店，是日系穿搭控的朝聖指南。",
          "url": "https://www.threads.com/@arvanndch/post/DZpEG61D00M"
        },
        {
          "title": "夏日防曬穿搭提案：機能、少女感與美式復古的碰撞",
          "description": "分析多款防曬外套，包含 NOCONTENT 的美式復古教練外套與 HELINOX 的機能風，展現夏季實用與時髦的平衡。",
          "url": "https://www.threads.com/@miette.oo/post/DZ_rUs_D8Ga"
        },
        {
          "title": "韓系男裝的低成本穿搭美學",
          "description": "探討韓國男裝如何透過簡單單品搭出高大眾接受度的韓男風格，適合尋求快速出門穿搭邏輯的讀者。",
          "url": "https://www.threads.com/@___viefolle/post/C8yi1nVSVvq"
        }
      ]
    },
    "posts": [
      {
        "permalink": "https://www.threads.com/@___viefolle/post/C8yi1nVSVvq",
        "username": "___viefolle",
        "post_date": "2024-6-29",
        "content": "韓國男裝超便宜⋯雖然是常見的幾件衣服但真的隨便搭都好看 我能馬上生出十套好看的韓男穿搭吧（但就是大眾風/不是特別&有個性高級的那種）",
        "likes": 977,
        "comments": 30,
        "reposts": 37,
        "shares": 183,
        "keyword": "男生穿搭"
      },
      {
        "permalink": "https://www.threads.com/@lxz20002000/post/DVIPpIWkyP7",
        "username": "lxz20002000",
        "post_date": "2026-2-24",
        "content": "男生想盡快學會穿搭\n很簡單\n這裡有範本供照抄\n教你從台男秒變日系潮男昭和時代的",
        "likes": 3441,
        "comments": 541,
        "reposts": 76,
        "shares": 2787,
        "keyword": "男生穿搭"
      },
      {
        "permalink": "https://www.threads.com/@emipeily.fr/post/DTiP1dYkVfg",
        "username": "emipeily.fr",
        "post_date": "2026-1-15",
        "content": "這台印出來是美式復古「軟膠片」🎥\n半透明很有質感！還能撕下來當貼紙\n🛖目前只能現金 店裡無法換鈔\n開到凌晨2:00建議晚上去不太排隊",
        "likes": 9621,
        "comments": 32,
        "reposts": 593,
        "shares": 7979,
        "keyword": "美式復古"
      },
      {
        "permalink": "https://www.threads.com/@leo__524/post/DY4bkf8kzS4",
        "username": "leo__524",
        "post_date": "2026-5-28",
        "content": "台北新開幕的『 美式復古餐廳 』 ✨\n鄰近中山站商圈 📍\n空間融入50年代美式 diner 元素 🇺🇸\n提供漢堡🍔、炸雞、奶昔和漂浮系列飲品 🍒\n晚上這裡一定更有氛圍 .ᐟ.ᐟ",
        "likes": 6931,
        "comments": 186,
        "reposts": 451,
        "shares": 6216,
        "keyword": "美式復古"
      },
      {
        "permalink": "https://www.threads.com/@miette.oo/post/DZ_rUs_D8Ga",
        "username": "miette.oo",
        "post_date": "3天",
        "content": "六月都還沒過完就已經快被曬死了....已黑三階\n決定來跟大家分享幾件今年喜歡的防曬外套 ☀️\n1️⃣ HELINOX ( #機能風 sporty )\n韓國有名的戶外裝備品牌，大家一定多多少少有耳聞！他們家防曬外套也做得很好看——版型寬鬆而且非常輕薄（真的超級輕薄沒再開玩笑）白色、黑色、深咖三色隨便搭都很有型＞＜\n要去爬山、騎車，或只是隨便晃晃，這一件都可以滿足✊🏻\n2️⃣ RONRON ( #少女可愛 )\n不喜歡穿起來太運動感、平常穿搭走比較可愛路線又想防曬的友寶，這件完全就是你ㄉ夏日防曬穿搭首選 pick、微透材質加上柔和的顏色，超適合搭背心、短裙或短褲～\n3️⃣ YEGG ( #鬼馬風 )\nYEGG 這次連防曬外套都加上他們的招牌設計啦\n大喊三聲 kiyo～且完全沒有要放過格紋控🥹\n他們家的衣服設計總是給人一種鬼靈精怪的港覺，推薦給各位穿搭魔人，或是不想跟別人撞款的友寶🫶🏻\n4️⃣ NOCONTENT ( #美式復古 )\n這次介紹中唯一一件教練外套版型的防曬外套",
        "likes": 251,
        "comments": 3,
        "reposts": 12,
        "shares": 150,
        "keyword": "美式復古"
      },
      {
        "permalink": "https://www.threads.com/@sszu.y/post/DZZ8i_8kzFT",
        "username": "sszu.y",
        "post_date": "2026-6-10",
        "content": "發現了一個很厲害的app\n把原本平平無奇的照片變成超有美式復古氛圍的閃光燈照😆🤎",
        "likes": 4983,
        "comments": 44,
        "reposts": 176,
        "shares": 1094,
        "keyword": "美式復古"
      },
      {
        "permalink": "https://www.threads.com/@arvanndch/post/DZpEG61D00M",
        "username": "arvanndch",
        "post_date": "2026-6-16",
        "content": "這間會不會是大阪日牌最多的選物店啊？\n選品橫跨戶外機能、美式復古到日系極簡✨\n從DAIWA PIER39、紫標The North Face、Patagonia、L.L.Bean、Gramicci、nanamica、Wild Things 這類城市機能品牌。\n再到以經典軍工裝、日本丹寧聞名的orSlow、Ordinary Fits、Kaptain Sunshine、Graphpaper。\n當然日本選物店的人氣質感品牌AURALEE、YAECA、BATONER也一點都沒少，再搭配法國經典皮鞋品牌 Paraboot，輕鬆打造出沉穩內斂的都會風格。\n近年在東京選物店討論度很高的 SEDAN ALL-PURPOSE、NOROLL、Tacoma Fuji Records等個性日牌這裡也找得到🙌",
        "likes": 553,
        "comments": 40,
        "reposts": 16,
        "shares": 412,
        "keyword": "美式復古"
      },
      {
        "permalink": "https://www.threads.com/@yukiii_tete.v/post/DZ-cR4fG_vv",
        "username": "yukiii_tete.v",
        "post_date": "3天",
        "content": "有阿米女神扒出来泰酱用的是哪款面膜了嘛！\n蹲蹲蹲",
        "likes": 71,
        "comments": 18,
        "reposts": 2,
        "shares": 11,
        "keyword": "阿美咔嘰"
      },
      {
        "permalink": "https://www.threads.com/@yakiii_js/post/DZTsLDKj8bq",
        "username": "yakiii_js",
        "post_date": "2026-6-8",
        "content": "連阿米棒也搶不到\n我還能幹嘛…",
        "likes": 32,
        "comments": 16,
        "reposts": 1,
        "shares": 2,
        "keyword": "阿美咔嘰"
      },
      {
        "permalink": "https://www.threads.com/@weeei_1125/post/DXbyalqlPr_",
        "username": "weeei_1125",
        "post_date": "2026-4-22",
        "content": "身邊朋友一直都在說原住民很頂\n.\n.\n.\n該集合了 蓋個樓了🔥",
        "likes": 32000,
        "comments": 3127,
        "reposts": 706,
        "shares": 5070,
        "keyword": "阿美咔嘰"
      },
      {
        "permalink": "https://www.threads.com/@lemon.coser/post/DXgJmfkjku6",
        "username": "lemon.coser",
        "post_date": "2026-4-24",
        "content": "阿美族 👀",
        "likes": 10000,
        "comments": 115,
        "reposts": 57,
        "shares": 411,
        "keyword": "阿美咔嘰"
      },
      {
        "permalink": "https://www.threads.com/@yut.128/post/DZEcpIQGAmz",
        "username": "yut.128",
        "post_date": "2026-6-2",
        "content": "阿米們來報喜！！！",
        "likes": 35,
        "comments": 33,
        "reposts": 0,
        "shares": 0,
        "keyword": "阿美咔嘰"
      }
    ]
  },
  "2026-06-27": {
    "keyword_tags": [
      "男生穿搭",
      "美式復古",
      "阿美咔嘰"
    ],
    "ai_summary": {
      "title": "今日 Threads 穿搭趨勢與復古風格分析",
      "intro": "今日 Threads 社群的穿搭討論高度集中於「高質感基礎單品」與「美式復古風格」的進階演繹。數據分析顯示，男性用戶對於「素面但不單調」的服飾有著極大渴求，正積極尋找能快速提升穿搭感的關鍵單品。同時，美式復古風依舊穩健，大眾開始尋求帶有細節圖騰而非純素色的基礎款。此外，一則關於各國穿搭美學本質（身型條件）的深度討論獲得了極高關注，顯示社群對時尚的思考正從服裝本身延伸至體態美學。",
      "highlights": [
        {
          "title": "韓美日法風格的本質熱議",
          "description": "獲得超過 7000 個讚的高關注貼文，精闢分析了無論是韓系、日系、美式或法式，其穿搭的核心魅力往往來自於「纖瘦的體態」，引發大量社群共鳴與對審美標準的思考。",
          "url": "https://www.threads.com/@xwwxz_1221/post/DWLmiYzFYj4"
        },
        {
          "title": "穿搭新手男性的救星推薦",
          "description": "此貼文成功鎖定「不擅長穿搭」的男性族群，推薦了據稱能直接「鎖在身上」的必備單品，在短時間內獲得超過三千次點讚，顯示出高效能穿搭指南在 Threads 上的強大影響力。",
          "url": "https://www.threads.com/@omgomg_8887/post/DTFxW7zE7ZR"
        },
        {
          "title": "美式復古基礎單品的需求轉向",
          "description": "網友積極尋找帶有文字與圖案設計的美式風格短袖，並強調「不要只有素踢」，反映出美式復古愛好者正從極簡風轉向追求具備視覺亮點的基礎款式。",
          "url": "https://www.threads.com/@17zzzzzzzz_/post/DW_j1jcD_zw"
        },
        {
          "title": "男裝素面質感化的選購需求",
          "description": "用戶詢問如何購買「素面但不單調」的外套與上衣，這類對細節與質感的特定需求，顯示男裝市場正朝向更有質感的極簡主義演進。",
          "url": "https://www.threads.com/@_g3cpyjk/post/DI0XlCfPr2V"
        }
      ]
    },
    "posts": [
      {
        "permalink": "https://www.threads.com/@_g3cpyjk/post/DI0XlCfPr2V",
        "username": "_g3cpyjk",
        "post_date": "2025-4-24",
        "content": "男生都去哪裡買衣服外套的 那種素面 但是看起來不會很單調的 求求了 謝謝大家 男生穿搭",
        "likes": 42,
        "comments": 27,
        "reposts": 8,
        "shares": 0,
        "keyword": "男生穿搭"
      },
      {
        "permalink": "https://www.threads.com/@omgomg_8887/post/DTFxW7zE7ZR",
        "username": "omgomg_8887",
        "post_date": "2026-1-4",
        "content": "男生不懂穿搭的 直接把這件鎖在身上🫡",
        "likes": 3446,
        "comments": 116,
        "reposts": 94,
        "shares": 2653,
        "keyword": "男生穿搭"
      },
      {
        "permalink": "https://www.threads.com/@unn._.2026/post/DZzSGTmE2_o",
        "username": "unn._.2026",
        "post_date": "6天",
        "content": "求一些美式風格的穿戴甲😛🙌🏻🙌🏻",
        "likes": 9,
        "comments": 13,
        "reposts": 0,
        "shares": 0,
        "keyword": "美式復古"
      },
      {
        "permalink": "https://www.threads.com/@xwwxz_1221/post/DWLmiYzFYj4",
        "username": "xwwxz_1221",
        "post_date": "2026-3-22",
        "content": "其实韩式日式美式法式穿搭精髓都是薄薄一片人😭😭😭😭",
        "likes": 7482,
        "comments": 43,
        "reposts": 393,
        "shares": 148,
        "keyword": "美式復古"
      },
      {
        "permalink": "https://www.threads.com/@pollyllam/post/DZu8zXtjxJu",
        "username": "pollyllam",
        "post_date": "2026-6-18",
        "content": "這麼正那麼靚🥰🥰🥰\n復古風是什麼活動呢.....期待💜\nyiminghay",
        "likes": 158,
        "comments": 12,
        "reposts": 2,
        "shares": 0,
        "keyword": "美式復古"
      },
      {
        "permalink": "https://www.threads.com/@skwnkxj/post/DZsEy3LlJr6",
        "username": "skwnkxj",
        "post_date": "2026-6-17",
        "content": "南實踐跟亞洲的時尚設計選哪個好！！！（苦惱）",
        "likes": 68,
        "comments": 15,
        "reposts": 22,
        "shares": 0,
        "keyword": "美式復古"
      },
      {
        "permalink": "https://www.threads.com/@17zzzzzzzz_/post/DW_j1jcD_zw",
        "username": "17zzzzzzzz_",
        "post_date": "2026-4-11",
        "content": "誰有賣那種比較美式風格的衣服😭\n最近很缺那種一般基礎款的短袖\n但上面有文字 圖案等等的\n不要只有素踢的那種\n其他美式服裝也看看😚",
        "likes": 186,
        "comments": 53,
        "reposts": 4,
        "shares": 62,
        "keyword": "美式復古"
      },
      {
        "permalink": "https://www.threads.com/@armymimimi7/post/DZD6hOaAeCC",
        "username": "armymimimi7",
        "post_date": "2026-6-1",
        "content": "好想和阿米互关。",
        "likes": 8,
        "comments": 13,
        "reposts": 0,
        "shares": 0,
        "keyword": "阿美咔嘰"
      },
      {
        "permalink": "https://www.threads.com/@a_168_88/post/DXWZxn6mdVQ",
        "username": "a_168_88",
        "post_date": "2026-4-20",
        "content": "高火安美進新娃了\nSumimi初華Get!\n我看裡面還有阿拉蕾\n甜甜圈女士也有🍩",
        "likes": 378,
        "comments": 29,
        "reposts": 8,
        "shares": 168,
        "keyword": "阿美咔嘰"
      },
      {
        "permalink": "https://www.threads.com/@shinchan_.85/post/DMYR30YByQA",
        "username": "shinchan_.85",
        "post_date": "2025-7-21",
        "content": "阿美：我人生中第一次被搭訕這麼開心。\n深夜讓大家笑笑沒煩惱\n（絕對不是因為魔性笑聲過多才剪出來）\n@alice19971011",
        "likes": 10000,
        "comments": 280,
        "reposts": 417,
        "shares": 579,
        "keyword": "阿美咔嘰"
      },
      {
        "permalink": "https://www.threads.com/@kelly__0227/post/DOiRM4Tkomn",
        "username": "kelly__0227",
        "post_date": "2025-9-13",
        "content": "米干都只吃阿美⋯還有推薦的嗎🤣\n我知道的只有那幾家大間的哈哈哈",
        "likes": 1190,
        "comments": 117,
        "reposts": 59,
        "shares": 529,
        "keyword": "阿美咔嘰"
      },
      {
        "permalink": "https://www.threads.com/@diyalv_420/post/DYw8nQ2Dzig",
        "username": "diyalv_420",
        "post_date": "2026-5-25",
        "content": "阿米女神和我互关好不😋",
        "likes": 30,
        "comments": 32,
        "reposts": 0,
        "shares": 0,
        "keyword": "阿美咔嘰"
      }
    ]
  }
}